{"primaryContentSections":[{"kind":"declarations","declarations":[{"tokens":[{"kind":"keyword","text":"init"},{"kind":"text","text":"("},{"kind":"externalParam","text":"authenticationConfig"},{"kind":"text","text":": "},{"kind":"typeIdentifier","identifier":"doc:\/\/AWSAppflow\/documentation\/AWSAppflow\/AppflowClientTypes","preciseIdentifier":"s:10AWSAppflow18AppflowClientTypesO","text":"AppflowClientTypes"},{"kind":"text","text":"."},{"kind":"typeIdentifier","identifier":"doc:\/\/AWSAppflow\/documentation\/AWSAppflow\/AppflowClientTypes\/AuthenticationConfig","preciseIdentifier":"s:10AWSAppflow18AppflowClientTypesO20AuthenticationConfigV","text":"AuthenticationConfig"},{"kind":"text","text":"? = nil, "},{"kind":"externalParam","text":"canUseAsDestination"},{"kind":"text","text":": "},{"kind":"typeIdentifier","text":"Bool","preciseIdentifier":"s:Sb"},{"kind":"text","text":" = false, "},{"kind":"externalParam","text":"canUseAsSource"},{"kind":"text","text":": "},{"kind":"typeIdentifier","text":"Bool","preciseIdentifier":"s:Sb"},{"kind":"text","text":" = false, "},{"kind":"externalParam","text":"connectorArn"},{"kind":"text","text":": "},{"kind":"typeIdentifier","text":"String","preciseIdentifier":"s:SS"},{"kind":"text","text":"? = nil, "},{"kind":"externalParam","text":"connectorDescription"},{"kind":"text","text":": "},{"kind":"typeIdentifier","text":"String","preciseIdentifier":"s:SS"},{"kind":"text","text":"? = nil, "},{"kind":"externalParam","text":"connectorLabel"},{"kind":"text","text":": "},{"kind":"typeIdentifier","text":"String","preciseIdentifier":"s:SS"},{"kind":"text","text":"? = nil, "},{"kind":"externalParam","text":"connectorMetadata"},{"kind":"text","text":": "},{"kind":"typeIdentifier","identifier":"doc:\/\/AWSAppflow\/documentation\/AWSAppflow\/AppflowClientTypes","preciseIdentifier":"s:10AWSAppflow18AppflowClientTypesO","text":"AppflowClientTypes"},{"kind":"text","text":"."},{"kind":"typeIdentifier","identifier":"doc:\/\/AWSAppflow\/documentation\/AWSAppflow\/AppflowClientTypes\/ConnectorMetadata","preciseIdentifier":"s:10AWSAppflow18AppflowClientTypesO17ConnectorMetadataV","text":"ConnectorMetadata"},{"kind":"text","text":"? = nil, "},{"kind":"externalParam","text":"connectorModes"},{"kind":"text","text":": ["},{"kind":"typeIdentifier","text":"String","preciseIdentifier":"s:SS"},{"kind":"text","text":"]? = nil, "},{"kind":"externalParam","text":"connectorName"},{"kind":"text","text":": "},{"kind":"typeIdentifier","text":"String","preciseIdentifier":"s:SS"},{"kind":"text","text":"? = nil, "},{"kind":"externalParam","text":"connectorOwner"},{"kind":"text","text":": "},{"kind":"typeIdentifier","text":"String","preciseIdentifier":"s:SS"},{"kind":"text","text":"? = nil, "},{"kind":"externalParam","text":"connectorProvisioningConfig"},{"kind":"text","text":": "},{"kind":"typeIdentifier","identifier":"doc:\/\/AWSAppflow\/documentation\/AWSAppflow\/AppflowClientTypes","preciseIdentifier":"s:10AWSAppflow18AppflowClientTypesO","text":"AppflowClientTypes"},{"kind":"text","text":"."},{"kind":"typeIdentifier","identifier":"doc:\/\/AWSAppflow\/documentation\/AWSAppflow\/AppflowClientTypes\/ConnectorProvisioningConfig","preciseIdentifier":"s:10AWSAppflow18AppflowClientTypesO27ConnectorProvisioningConfigV","text":"ConnectorProvisioningConfig"},{"kind":"text","text":"? = nil, "},{"kind":"externalParam","text":"connectorProvisioningType"},{"kind":"text","text":": "},{"kind":"typeIdentifier","identifier":"doc:\/\/AWSAppflow\/documentation\/AWSAppflow\/AppflowClientTypes","preciseIdentifier":"s:10AWSAppflow18AppflowClientTypesO","text":"AppflowClientTypes"},{"kind":"text","text":"."},{"kind":"typeIdentifier","identifier":"doc:\/\/AWSAppflow\/documentation\/AWSAppflow\/AppflowClientTypes\/ConnectorProvisioningType","preciseIdentifier":"s:10AWSAppflow18AppflowClientTypesO25ConnectorProvisioningTypeO","text":"ConnectorProvisioningType"},{"kind":"text","text":"? = nil, "},{"kind":"externalParam","text":"connectorRuntimeSettings"},{"kind":"text","text":": ["},{"kind":"typeIdentifier","identifier":"doc:\/\/AWSAppflow\/documentation\/AWSAppflow\/AppflowClientTypes","preciseIdentifier":"s:10AWSAppflow18AppflowClientTypesO","text":"AppflowClientTypes"},{"kind":"text","text":"."},{"kind":"typeIdentifier","identifier":"doc:\/\/AWSAppflow\/documentation\/AWSAppflow\/AppflowClientTypes\/ConnectorRuntimeSetting","preciseIdentifier":"s:10AWSAppflow18AppflowClientTypesO23ConnectorRuntimeSettingV","text":"ConnectorRuntimeSetting"},{"kind":"text","text":"]? = nil, "},{"kind":"externalParam","text":"connectorType"},{"kind":"text","text":": "},{"kind":"typeIdentifier","identifier":"doc:\/\/AWSAppflow\/documentation\/AWSAppflow\/AppflowClientTypes","preciseIdentifier":"s:10AWSAppflow18AppflowClientTypesO","text":"AppflowClientTypes"},{"kind":"text","text":"."},{"kind":"typeIdentifier","identifier":"doc:\/\/AWSAppflow\/documentation\/AWSAppflow\/AppflowClientTypes\/ConnectorType","preciseIdentifier":"s:10AWSAppflow18AppflowClientTypesO13ConnectorTypeO","text":"ConnectorType"},{"kind":"text","text":"? = nil, "},{"kind":"externalParam","text":"connectorVersion"},{"kind":"text","text":": "},{"kind":"typeIdentifier","text":"String","preciseIdentifier":"s:SS"},{"kind":"text","text":"? = nil, "},{"kind":"externalParam","text":"isPrivateLinkEnabled"},{"kind":"text","text":": "},{"kind":"typeIdentifier","text":"Bool","preciseIdentifier":"s:Sb"},{"kind":"text","text":" = false, "},{"kind":"externalParam","text":"isPrivateLinkEndpointUrlRequired"},{"kind":"text","text":": "},{"kind":"typeIdentifier","text":"Bool","preciseIdentifier":"s:Sb"},{"kind":"text","text":" = false, "},{"kind":"externalParam","text":"logoURL"},{"kind":"text","text":": "},{"kind":"typeIdentifier","text":"String","preciseIdentifier":"s:SS"},{"kind":"text","text":"? = nil, "},{"kind":"externalParam","text":"registeredAt"},{"kind":"text","text":": "},{"kind":"typeIdentifier","text":"Date","preciseIdentifier":"s:13ClientRuntime4Datea"},{"kind":"text","text":"? = nil, "},{"kind":"externalParam","text":"registeredBy"},{"kind":"text","text":": "},{"kind":"typeIdentifier","text":"String","preciseIdentifier":"s:SS"},{"kind":"text","text":"? = nil, "},{"kind":"externalParam","text":"supportedApiVersions"},{"kind":"text","text":": ["},{"kind":"typeIdentifier","text":"String","preciseIdentifier":"s:SS"},{"kind":"text","text":"]? = nil, "},{"kind":"externalParam","text":"supportedDestinationConnectors"},{"kind":"text","text":": ["},{"kind":"typeIdentifier","identifier":"doc:\/\/AWSAppflow\/documentation\/AWSAppflow\/AppflowClientTypes","preciseIdentifier":"s:10AWSAppflow18AppflowClientTypesO","text":"AppflowClientTypes"},{"kind":"text","text":"."},{"kind":"typeIdentifier","identifier":"doc:\/\/AWSAppflow\/documentation\/AWSAppflow\/AppflowClientTypes\/ConnectorType","preciseIdentifier":"s:10AWSAppflow18AppflowClientTypesO13ConnectorTypeO","text":"ConnectorType"},{"kind":"text","text":"]? = nil, "},{"kind":"externalParam","text":"supportedOperators"},{"kind":"text","text":": ["},{"kind":"typeIdentifier","identifier":"doc:\/\/AWSAppflow\/documentation\/AWSAppflow\/AppflowClientTypes","preciseIdentifier":"s:10AWSAppflow18AppflowClientTypesO","text":"AppflowClientTypes"},{"kind":"text","text":"."},{"kind":"typeIdentifier","identifier":"doc:\/\/AWSAppflow\/documentation\/AWSAppflow\/AppflowClientTypes\/Operators","preciseIdentifier":"s:10AWSAppflow18AppflowClientTypesO9OperatorsO","text":"Operators"},{"kind":"text","text":"]? = nil, "},{"kind":"externalParam","text":"supportedSchedulingFrequencies"},{"kind":"text","text":": ["},{"kind":"typeIdentifier","identifier":"doc:\/\/AWSAppflow\/documentation\/AWSAppflow\/AppflowClientTypes","preciseIdentifier":"s:10AWSAppflow18AppflowClientTypesO","text":"AppflowClientTypes"},{"kind":"text","text":"."},{"kind":"typeIdentifier","identifier":"doc:\/\/AWSAppflow\/documentation\/AWSAppflow\/AppflowClientTypes\/ScheduleFrequencyType","preciseIdentifier":"s:10AWSAppflow18AppflowClientTypesO21ScheduleFrequencyTypeO","text":"ScheduleFrequencyType"},{"kind":"text","text":"]? = nil, "},{"kind":"externalParam","text":"supportedTriggerTypes"},{"kind":"text","text":": ["},{"kind":"typeIdentifier","identifier":"doc:\/\/AWSAppflow\/documentation\/AWSAppflow\/AppflowClientTypes","preciseIdentifier":"s:10AWSAppflow18AppflowClientTypesO","text":"AppflowClientTypes"},{"kind":"text","text":"."},{"kind":"typeIdentifier","identifier":"doc:\/\/AWSAppflow\/documentation\/AWSAppflow\/AppflowClientTypes\/TriggerType","preciseIdentifier":"s:10AWSAppflow18AppflowClientTypesO11TriggerTypeO","text":"TriggerType"},{"kind":"text","text":"]? = nil, "},{"kind":"externalParam","text":"supportedWriteOperations"},{"kind":"text","text":": ["},{"kind":"typeIdentifier","identifier":"doc:\/\/AWSAppflow\/documentation\/AWSAppflow\/AppflowClientTypes","preciseIdentifier":"s:10AWSAppflow18AppflowClientTypesO","text":"AppflowClientTypes"},{"kind":"text","text":"."},{"kind":"typeIdentifier","identifier":"doc:\/\/AWSAppflow\/documentation\/AWSAppflow\/AppflowClientTypes\/WriteOperationType","preciseIdentifier":"s:10AWSAppflow18AppflowClientTypesO18WriteOperationTypeO","text":"WriteOperationType"},{"kind":"text","text":"]? = nil)"}],"languages":["swift"],"platforms":["macOS"]}]}],"schemaVersion":{"major":0,"minor":3,"patch":0},"sections":[],"variants":[{"paths":["\/documentation\/awsappflow\/appflowclienttypes\/connectorconfiguration\/init(authenticationconfig:canuseasdestination:canuseassource:connectorarn:connectordescription:connectorlabel:connectormetadata:connectormodes:connectorname:connectorowner:connectorprovisioningconfig:connectorprovisioningtype:connectorrunti-58qin"],"traits":[{"interfaceLanguage":"swift"}]}],"identifier":{"url":"doc:\/\/AWSAppflow\/documentation\/AWSAppflow\/AppflowClientTypes\/ConnectorConfiguration\/init(authenticationConfig:canUseAsDestination:canUseAsSource:connectorArn:connectorDescription:connectorLabel:connectorMetadata:connectorModes:connectorName:connectorOwner:connectorProvisioningConfig:connectorProvisioningType:connectorRuntimeSettings:connectorType:connectorVersion:isPrivateLinkEnabled:isPrivateLinkEndpointUrlRequired:logoURL:registeredAt:registeredBy:supportedApiVersions:supportedDestinationConnectors:supportedOperators:supportedSchedulingFrequencies:supportedTriggerTypes:supportedWriteOperations:)","interfaceLanguage":"swift"},"kind":"symbol","metadata":{"fragments":[{"kind":"identifier","text":"init"},{"kind":"text","text":"("},{"kind":"externalParam","text":"authenticationConfig"},{"kind":"text","text":": "},{"kind":"typeIdentifier","text":"AppflowClientTypes","preciseIdentifier":"s:10AWSAppflow18AppflowClientTypesO"},{"kind":"text","text":"."},{"kind":"typeIdentifier","text":"AuthenticationConfig","preciseIdentifier":"s:10AWSAppflow18AppflowClientTypesO20AuthenticationConfigV"},{"kind":"text","text":"?, "},{"kind":"externalParam","text":"canUseAsDestination"},{"kind":"text","text":": "},{"kind":"typeIdentifier","text":"Bool","preciseIdentifier":"s:Sb"},{"kind":"text","text":", "},{"kind":"externalParam","text":"canUseAsSource"},{"kind":"text","text":": "},{"kind":"typeIdentifier","text":"Bool","preciseIdentifier":"s:Sb"},{"kind":"text","text":", "},{"kind":"externalParam","text":"connectorArn"},{"kind":"text","text":": "},{"kind":"typeIdentifier","text":"String","preciseIdentifier":"s:SS"},{"kind":"text","text":"?, "},{"kind":"externalParam","text":"connectorDescription"},{"kind":"text","text":": "},{"kind":"typeIdentifier","text":"String","preciseIdentifier":"s:SS"},{"kind":"text","text":"?, "},{"kind":"externalParam","text":"connectorLabel"},{"kind":"text","text":": "},{"kind":"typeIdentifier","text":"String","preciseIdentifier":"s:SS"},{"kind":"text","text":"?, "},{"kind":"externalParam","text":"connectorMetadata"},{"kind":"text","text":": "},{"kind":"typeIdentifier","text":"AppflowClientTypes","preciseIdentifier":"s:10AWSAppflow18AppflowClientTypesO"},{"kind":"text","text":"."},{"kind":"typeIdentifier","text":"ConnectorMetadata","preciseIdentifier":"s:10AWSAppflow18AppflowClientTypesO17ConnectorMetadataV"},{"kind":"text","text":"?, "},{"kind":"externalParam","text":"connectorModes"},{"kind":"text","text":": ["},{"kind":"typeIdentifier","text":"String","preciseIdentifier":"s:SS"},{"kind":"text","text":"]?, "},{"kind":"externalParam","text":"connectorName"},{"kind":"text","text":": "},{"kind":"typeIdentifier","text":"String","preciseIdentifier":"s:SS"},{"kind":"text","text":"?, "},{"kind":"externalParam","text":"connectorOwner"},{"kind":"text","text":": "},{"kind":"typeIdentifier","text":"String","preciseIdentifier":"s:SS"},{"kind":"text","text":"?, "},{"kind":"externalParam","text":"connectorProvisioningConfig"},{"kind":"text","text":": "},{"kind":"typeIdentifier","text":"AppflowClientTypes","preciseIdentifier":"s:10AWSAppflow18AppflowClientTypesO"},{"kind":"text","text":"."},{"kind":"typeIdentifier","text":"ConnectorProvisioningConfig","preciseIdentifier":"s:10AWSAppflow18AppflowClientTypesO27ConnectorProvisioningConfigV"},{"kind":"text","text":"?, "},{"kind":"externalParam","text":"connectorProvisioningType"},{"kind":"text","text":": "},{"kind":"typeIdentifier","text":"AppflowClientTypes","preciseIdentifier":"s:10AWSAppflow18AppflowClientTypesO"},{"kind":"text","text":"."},{"kind":"typeIdentifier","text":"ConnectorProvisioningType","preciseIdentifier":"s:10AWSAppflow18AppflowClientTypesO25ConnectorProvisioningTypeO"},{"kind":"text","text":"?, "},{"kind":"externalParam","text":"connectorRuntimeSettings"},{"kind":"text","text":": ["},{"kind":"typeIdentifier","text":"AppflowClientTypes","preciseIdentifier":"s:10AWSAppflow18AppflowClientTypesO"},{"kind":"text","text":"."},{"kind":"typeIdentifier","text":"ConnectorRuntimeSetting","preciseIdentifier":"s:10AWSAppflow18AppflowClientTypesO23ConnectorRuntimeSettingV"},{"kind":"text","text":"]?, "},{"kind":"externalParam","text":"connectorType"},{"kind":"text","text":": "},{"kind":"typeIdentifier","text":"AppflowClientTypes","preciseIdentifier":"s:10AWSAppflow18AppflowClientTypesO"},{"kind":"text","text":"."},{"kind":"typeIdentifier","text":"ConnectorType","preciseIdentifier":"s:10AWSAppflow18AppflowClientTypesO13ConnectorTypeO"},{"kind":"text","text":"?, "},{"kind":"externalParam","text":"connectorVersion"},{"kind":"text","text":": "},{"kind":"typeIdentifier","text":"String","preciseIdentifier":"s:SS"},{"kind":"text","text":"?, "},{"kind":"externalParam","text":"isPrivateLinkEnabled"},{"kind":"text","text":": "},{"kind":"typeIdentifier","text":"Bool","preciseIdentifier":"s:Sb"},{"kind":"text","text":", "},{"kind":"externalParam","text":"isPrivateLinkEndpointUrlRequired"},{"kind":"text","text":": "},{"kind":"typeIdentifier","text":"Bool","preciseIdentifier":"s:Sb"},{"kind":"text","text":", "},{"kind":"externalParam","text":"logoURL"},{"kind":"text","text":": "},{"kind":"typeIdentifier","text":"String","preciseIdentifier":"s:SS"},{"kind":"text","text":"?, "},{"kind":"externalParam","text":"registeredAt"},{"kind":"text","text":": "},{"kind":"typeIdentifier","text":"Date","preciseIdentifier":"s:13ClientRuntime4Datea"},{"kind":"text","text":"?, "},{"kind":"externalParam","text":"registeredBy"},{"kind":"text","text":": "},{"kind":"typeIdentifier","text":"String","preciseIdentifier":"s:SS"},{"kind":"text","text":"?, "},{"kind":"externalParam","text":"supportedApiVersions"},{"kind":"text","text":": ["},{"kind":"typeIdentifier","text":"String","preciseIdentifier":"s:SS"},{"kind":"text","text":"]?, "},{"kind":"externalParam","text":"supportedDestinationConnectors"},{"kind":"text","text":": ["},{"kind":"typeIdentifier","text":"AppflowClientTypes","preciseIdentifier":"s:10AWSAppflow18AppflowClientTypesO"},{"kind":"text","text":"."},{"kind":"typeIdentifier","text":"ConnectorType","preciseIdentifier":"s:10AWSAppflow18AppflowClientTypesO13ConnectorTypeO"},{"kind":"text","text":"]?, "},{"kind":"externalParam","text":"supportedOperators"},{"kind":"text","text":": ["},{"kind":"typeIdentifier","text":"AppflowClientTypes","preciseIdentifier":"s:10AWSAppflow18AppflowClientTypesO"},{"kind":"text","text":"."},{"kind":"typeIdentifier","text":"Operators","preciseIdentifier":"s:10AWSAppflow18AppflowClientTypesO9OperatorsO"},{"kind":"text","text":"]?, "},{"kind":"externalParam","text":"supportedSchedulingFrequencies"},{"kind":"text","text":": ["},{"kind":"typeIdentifier","text":"AppflowClientTypes","preciseIdentifier":"s:10AWSAppflow18AppflowClientTypesO"},{"kind":"text","text":"."},{"kind":"typeIdentifier","text":"ScheduleFrequencyType","preciseIdentifier":"s:10AWSAppflow18AppflowClientTypesO21ScheduleFrequencyTypeO"},{"kind":"text","text":"]?, "},{"kind":"externalParam","text":"supportedTriggerTypes"},{"kind":"text","text":": ["},{"kind":"typeIdentifier","text":"AppflowClientTypes","preciseIdentifier":"s:10AWSAppflow18AppflowClientTypesO"},{"kind":"text","text":"."},{"kind":"typeIdentifier","text":"TriggerType","preciseIdentifier":"s:10AWSAppflow18AppflowClientTypesO11TriggerTypeO"},{"kind":"text","text":"]?, "},{"kind":"externalParam","text":"supportedWriteOperations"},{"kind":"text","text":": ["},{"kind":"typeIdentifier","text":"AppflowClientTypes","preciseIdentifier":"s:10AWSAppflow18AppflowClientTypesO"},{"kind":"text","text":"."},{"kind":"typeIdentifier","text":"WriteOperationType","preciseIdentifier":"s:10AWSAppflow18AppflowClientTypesO18WriteOperationTypeO"},{"kind":"text","text":"]?)"}],"title":"init(authenticationConfig:canUseAsDestination:canUseAsSource:connectorArn:connectorDescription:connectorLabel:connectorMetadata:connectorModes:connectorName:connectorOwner:connectorProvisioningConfig:connectorProvisioningType:connectorRuntimeSettings:connectorType:connectorVersion:isPrivateLinkEnabled:isPrivateLinkEndpointUrlRequired:logoURL:registeredAt:registeredBy:supportedApiVersions:supportedDestinationConnectors:supportedOperators:supportedSchedulingFrequencies:supportedTriggerTypes:supportedWriteOperations:)","roleHeading":"Initializer","role":"symbol","symbolKind":"init","externalID":"s:10AWSAppflow18AppflowClientTypesO22ConnectorConfigurationV20authenticationConfig19canUseAsDestination0ijK6Source12connectorArn0N11Description0N5Label0N8Metadata0N5Modes0N4Name0N5Owner0n12ProvisioningH00nV4Type0N15RuntimeSettings0nW00N7Version20isPrivateLinkEnabled32isPrivateLinkEndpointUrlRequired7logoURL12registeredAt12registeredBy20supportedApiVersions09supportedL10Connectors18supportedOperators30supportedSchedulingFrequencies016supportedTriggerD024supportedWriteOperationsAeC014AuthenticationH0VSg_S2bSSSgA7_A7_AC0eR0VSgSaySSGSgA7_A7_AC0evH0VSgAC0evW0OSgSayAC0eX7SettingVGSgAC0eW0OSgA7_S2bA7_10Foundation4DateVSgA7_A12_SayA24_GSgSayAC9OperatorsOGSgSayAC017ScheduleFrequencyW0OGSgSayAC07TriggerW0OGSgSayAC014WriteOperationW0OGSgtcfc","modules":[{"name":"AWSAppflow"}]},"hierarchy":{"paths":[["doc:\/\/AWSAppflow\/documentation\/AWSAppflow","doc:\/\/AWSAppflow\/documentation\/AWSAppflow\/AppflowClientTypes","doc:\/\/AWSAppflow\/documentation\/AWSAppflow\/AppflowClientTypes\/ConnectorConfiguration"]]},"references":{"doc://AWSAppflow/documentation/AWSAppflow/AppflowClientTypes/ConnectorType":{"role":"symbol","title":"AppflowClientTypes.ConnectorType","fragments":[{"kind":"keyword","text":"enum"},{"kind":"text","text":" "},{"kind":"identifier","text":"ConnectorType"}],"abstract":[],"identifier":"doc:\/\/AWSAppflow\/documentation\/AWSAppflow\/AppflowClientTypes\/ConnectorType","kind":"symbol","type":"topic","navigatorTitle":[{"kind":"identifier","text":"ConnectorType"}],"url":"\/documentation\/awsappflow\/appflowclienttypes\/connectortype"},"doc://AWSAppflow/documentation/AWSAppflow/AppflowClientTypes":{"role":"symbol","title":"AppflowClientTypes","fragments":[{"kind":"keyword","text":"enum"},{"kind":"text","text":" "},{"kind":"identifier","text":"AppflowClientTypes"}],"abstract":[],"identifier":"doc:\/\/AWSAppflow\/documentation\/AWSAppflow\/AppflowClientTypes","kind":"symbol","type":"topic","navigatorTitle":[{"kind":"identifier","text":"AppflowClientTypes"}],"url":"\/documentation\/awsappflow\/appflowclienttypes"},"doc://AWSAppflow/documentation/AWSAppflow/AppflowClientTypes/WriteOperationType":{"role":"symbol","title":"AppflowClientTypes.WriteOperationType","fragments":[{"kind":"keyword","text":"enum"},{"kind":"text","text":" "},{"kind":"identifier","text":"WriteOperationType"}],"abstract":[{"type":"text","text":"The possible write operations in the destination connector. When this value is not provided, this defaults to the INSERT operation."}],"identifier":"doc:\/\/AWSAppflow\/documentation\/AWSAppflow\/AppflowClientTypes\/WriteOperationType","kind":"symbol","type":"topic","navigatorTitle":[{"kind":"identifier","text":"WriteOperationType"}],"url":"\/documentation\/awsappflow\/appflowclienttypes\/writeoperationtype"},"doc://AWSAppflow/documentation/AWSAppflow/AppflowClientTypes/ConnectorConfiguration":{"role":"symbol","title":"AppflowClientTypes.ConnectorConfiguration","fragments":[{"kind":"keyword","text":"struct"},{"kind":"text","text":" "},{"kind":"identifier","text":"ConnectorConfiguration"}],"abstract":[{"type":"text","text":"The configuration settings related to a given connector."}],"identifier":"doc:\/\/AWSAppflow\/documentation\/AWSAppflow\/AppflowClientTypes\/ConnectorConfiguration","kind":"symbol","type":"topic","navigatorTitle":[{"kind":"identifier","text":"ConnectorConfiguration"}],"url":"\/documentation\/awsappflow\/appflowclienttypes\/connectorconfiguration"},"doc://AWSAppflow/documentation/AWSAppflow":{"role":"collection","title":"AWSAppflow","abstract":[],"identifier":"doc:\/\/AWSAppflow\/documentation\/AWSAppflow","kind":"symbol","type":"topic","url":"\/documentation\/awsappflow"},"doc://AWSAppflow/documentation/AWSAppflow/AppflowClientTypes/ConnectorConfiguration/init(authenticationConfig:canUseAsDestination:canUseAsSource:connectorArn:connectorDescription:connectorLabel:connectorMetadata:connectorModes:connectorName:connectorOwner:connectorProvisioningConfig:connectorProvisioningType:connectorRuntimeSettings:connectorType:connectorVersion:isPrivateLinkEnabled:isPrivateLinkEndpointUrlRequired:logoURL:registeredAt:registeredBy:supportedApiVersions:supportedDestinationConnectors:supportedOperators:supportedSchedulingFrequencies:supportedTriggerTypes:supportedWriteOperations:)":{"role":"symbol","title":"init(authenticationConfig:canUseAsDestination:canUseAsSource:connectorArn:connectorDescription:connectorLabel:connectorMetadata:connectorModes:connectorName:connectorOwner:connectorProvisioningConfig:connectorProvisioningType:connectorRuntimeSettings:connectorType:connectorVersion:isPrivateLinkEnabled:isPrivateLinkEndpointUrlRequired:logoURL:registeredAt:registeredBy:supportedApiVersions:supportedDestinationConnectors:supportedOperators:supportedSchedulingFrequencies:supportedTriggerTypes:supportedWriteOperations:)","fragments":[{"kind":"identifier","text":"init"},{"kind":"text","text":"("},{"kind":"externalParam","text":"authenticationConfig"},{"kind":"text","text":": "},{"kind":"typeIdentifier","text":"AppflowClientTypes","preciseIdentifier":"s:10AWSAppflow18AppflowClientTypesO"},{"kind":"text","text":"."},{"kind":"typeIdentifier","text":"AuthenticationConfig","preciseIdentifier":"s:10AWSAppflow18AppflowClientTypesO20AuthenticationConfigV"},{"kind":"text","text":"?, "},{"kind":"externalParam","text":"canUseAsDestination"},{"kind":"text","text":": "},{"kind":"typeIdentifier","text":"Bool","preciseIdentifier":"s:Sb"},{"kind":"text","text":", "},{"kind":"externalParam","text":"canUseAsSource"},{"kind":"text","text":": "},{"kind":"typeIdentifier","text":"Bool","preciseIdentifier":"s:Sb"},{"kind":"text","text":", "},{"kind":"externalParam","text":"connectorArn"},{"kind":"text","text":": "},{"kind":"typeIdentifier","text":"String","preciseIdentifier":"s:SS"},{"kind":"text","text":"?, "},{"kind":"externalParam","text":"connectorDescription"},{"kind":"text","text":": "},{"kind":"typeIdentifier","text":"String","preciseIdentifier":"s:SS"},{"kind":"text","text":"?, "},{"kind":"externalParam","text":"connectorLabel"},{"kind":"text","text":": "},{"kind":"typeIdentifier","text":"String","preciseIdentifier":"s:SS"},{"kind":"text","text":"?, "},{"kind":"externalParam","text":"connectorMetadata"},{"kind":"text","text":": "},{"kind":"typeIdentifier","text":"AppflowClientTypes","preciseIdentifier":"s:10AWSAppflow18AppflowClientTypesO"},{"kind":"text","text":"."},{"kind":"typeIdentifier","text":"ConnectorMetadata","preciseIdentifier":"s:10AWSAppflow18AppflowClientTypesO17ConnectorMetadataV"},{"kind":"text","text":"?, "},{"kind":"externalParam","text":"connectorModes"},{"kind":"text","text":": ["},{"kind":"typeIdentifier","text":"String","preciseIdentifier":"s:SS"},{"kind":"text","text":"]?, "},{"kind":"externalParam","text":"connectorName"},{"kind":"text","text":": "},{"kind":"typeIdentifier","text":"String","preciseIdentifier":"s:SS"},{"kind":"text","text":"?, "},{"kind":"externalParam","text":"connectorOwner"},{"kind":"text","text":": "},{"kind":"typeIdentifier","text":"String","preciseIdentifier":"s:SS"},{"kind":"text","text":"?, "},{"kind":"externalParam","text":"connectorProvisioningConfig"},{"kind":"text","text":": "},{"kind":"typeIdentifier","text":"AppflowClientTypes","preciseIdentifier":"s:10AWSAppflow18AppflowClientTypesO"},{"kind":"text","text":"."},{"kind":"typeIdentifier","text":"ConnectorProvisioningConfig","preciseIdentifier":"s:10AWSAppflow18AppflowClientTypesO27ConnectorProvisioningConfigV"},{"kind":"text","text":"?, "},{"kind":"externalParam","text":"connectorProvisioningType"},{"kind":"text","text":": "},{"kind":"typeIdentifier","text":"AppflowClientTypes","preciseIdentifier":"s:10AWSAppflow18AppflowClientTypesO"},{"kind":"text","text":"."},{"kind":"typeIdentifier","text":"ConnectorProvisioningType","preciseIdentifier":"s:10AWSAppflow18AppflowClientTypesO25ConnectorProvisioningTypeO"},{"kind":"text","text":"?, "},{"kind":"externalParam","text":"connectorRuntimeSettings"},{"kind":"text","text":": ["},{"kind":"typeIdentifier","text":"AppflowClientTypes","preciseIdentifier":"s:10AWSAppflow18AppflowClientTypesO"},{"kind":"text","text":"."},{"kind":"typeIdentifier","text":"ConnectorRuntimeSetting","preciseIdentifier":"s:10AWSAppflow18AppflowClientTypesO23ConnectorRuntimeSettingV"},{"kind":"text","text":"]?, "},{"kind":"externalParam","text":"connectorType"},{"kind":"text","text":": "},{"kind":"typeIdentifier","text":"AppflowClientTypes","preciseIdentifier":"s:10AWSAppflow18AppflowClientTypesO"},{"kind":"text","text":"."},{"kind":"typeIdentifier","text":"ConnectorType","preciseIdentifier":"s:10AWSAppflow18AppflowClientTypesO13ConnectorTypeO"},{"kind":"text","text":"?, "},{"kind":"externalParam","text":"connectorVersion"},{"kind":"text","text":": "},{"kind":"typeIdentifier","text":"String","preciseIdentifier":"s:SS"},{"kind":"text","text":"?, "},{"kind":"externalParam","text":"isPrivateLinkEnabled"},{"kind":"text","text":": "},{"kind":"typeIdentifier","text":"Bool","preciseIdentifier":"s:Sb"},{"kind":"text","text":", "},{"kind":"externalParam","text":"isPrivateLinkEndpointUrlRequired"},{"kind":"text","text":": "},{"kind":"typeIdentifier","text":"Bool","preciseIdentifier":"s:Sb"},{"kind":"text","text":", "},{"kind":"externalParam","text":"logoURL"},{"kind":"text","text":": "},{"kind":"typeIdentifier","text":"String","preciseIdentifier":"s:SS"},{"kind":"text","text":"?, "},{"kind":"externalParam","text":"registeredAt"},{"kind":"text","text":": "},{"kind":"typeIdentifier","text":"Date","preciseIdentifier":"s:13ClientRuntime4Datea"},{"kind":"text","text":"?, "},{"kind":"externalParam","text":"registeredBy"},{"kind":"text","text":": "},{"kind":"typeIdentifier","text":"String","preciseIdentifier":"s:SS"},{"kind":"text","text":"?, "},{"kind":"externalParam","text":"supportedApiVersions"},{"kind":"text","text":": ["},{"kind":"typeIdentifier","text":"String","preciseIdentifier":"s:SS"},{"kind":"text","text":"]?, "},{"kind":"externalParam","text":"supportedDestinationConnectors"},{"kind":"text","text":": ["},{"kind":"typeIdentifier","text":"AppflowClientTypes","preciseIdentifier":"s:10AWSAppflow18AppflowClientTypesO"},{"kind":"text","text":"."},{"kind":"typeIdentifier","text":"ConnectorType","preciseIdentifier":"s:10AWSAppflow18AppflowClientTypesO13ConnectorTypeO"},{"kind":"text","text":"]?, "},{"kind":"externalParam","text":"supportedOperators"},{"kind":"text","text":": ["},{"kind":"typeIdentifier","text":"AppflowClientTypes","preciseIdentifier":"s:10AWSAppflow18AppflowClientTypesO"},{"kind":"text","text":"."},{"kind":"typeIdentifier","text":"Operators","preciseIdentifier":"s:10AWSAppflow18AppflowClientTypesO9OperatorsO"},{"kind":"text","text":"]?, "},{"kind":"externalParam","text":"supportedSchedulingFrequencies"},{"kind":"text","text":": ["},{"kind":"typeIdentifier","text":"AppflowClientTypes","preciseIdentifier":"s:10AWSAppflow18AppflowClientTypesO"},{"kind":"text","text":"."},{"kind":"typeIdentifier","text":"ScheduleFrequencyType","preciseIdentifier":"s:10AWSAppflow18AppflowClientTypesO21ScheduleFrequencyTypeO"},{"kind":"text","text":"]?, "},{"kind":"externalParam","text":"supportedTriggerTypes"},{"kind":"text","text":": ["},{"kind":"typeIdentifier","text":"AppflowClientTypes","preciseIdentifier":"s:10AWSAppflow18AppflowClientTypesO"},{"kind":"text","text":"."},{"kind":"typeIdentifier","text":"TriggerType","preciseIdentifier":"s:10AWSAppflow18AppflowClientTypesO11TriggerTypeO"},{"kind":"text","text":"]?, "},{"kind":"externalParam","text":"supportedWriteOperations"},{"kind":"text","text":": ["},{"kind":"typeIdentifier","text":"AppflowClientTypes","preciseIdentifier":"s:10AWSAppflow18AppflowClientTypesO"},{"kind":"text","text":"."},{"kind":"typeIdentifier","text":"WriteOperationType","preciseIdentifier":"s:10AWSAppflow18AppflowClientTypesO18WriteOperationTypeO"},{"kind":"text","text":"]?)"}],"abstract":[],"identifier":"doc:\/\/AWSAppflow\/documentation\/AWSAppflow\/AppflowClientTypes\/ConnectorConfiguration\/init(authenticationConfig:canUseAsDestination:canUseAsSource:connectorArn:connectorDescription:connectorLabel:connectorMetadata:connectorModes:connectorName:connectorOwner:connectorProvisioningConfig:connectorProvisioningType:connectorRuntimeSettings:connectorType:connectorVersion:isPrivateLinkEnabled:isPrivateLinkEndpointUrlRequired:logoURL:registeredAt:registeredBy:supportedApiVersions:supportedDestinationConnectors:supportedOperators:supportedSchedulingFrequencies:supportedTriggerTypes:supportedWriteOperations:)","kind":"symbol","type":"topic","url":"\/documentation\/awsappflow\/appflowclienttypes\/connectorconfiguration\/init(authenticationconfig:canuseasdestination:canuseassource:connectorarn:connectordescription:connectorlabel:connectormetadata:connectormodes:connectorname:connectorowner:connectorprovisioningconfig:connectorprovisioningtype:connectorrunti-58qin"},"doc://AWSAppflow/documentation/AWSAppflow/AppflowClientTypes/ConnectorRuntimeSetting":{"role":"symbol","title":"AppflowClientTypes.ConnectorRuntimeSetting","fragments":[{"kind":"keyword","text":"struct"},{"kind":"text","text":" "},{"kind":"identifier","text":"ConnectorRuntimeSetting"}],"abstract":[{"type":"text","text":"Contains information about the connector runtime settings that are required for flow execution."}],"identifier":"doc:\/\/AWSAppflow\/documentation\/AWSAppflow\/AppflowClientTypes\/ConnectorRuntimeSetting","kind":"symbol","type":"topic","navigatorTitle":[{"kind":"identifier","text":"ConnectorRuntimeSetting"}],"url":"\/documentation\/awsappflow\/appflowclienttypes\/connectorruntimesetting"},"doc://AWSAppflow/documentation/AWSAppflow/AppflowClientTypes/ConnectorProvisioningConfig":{"role":"symbol","title":"AppflowClientTypes.ConnectorProvisioningConfig","fragments":[{"kind":"keyword","text":"struct"},{"kind":"text","text":" "},{"kind":"identifier","text":"ConnectorProvisioningConfig"}],"abstract":[{"type":"text","text":"Contains information about the configuration of the connector being registered."}],"identifier":"doc:\/\/AWSAppflow\/documentation\/AWSAppflow\/AppflowClientTypes\/ConnectorProvisioningConfig","kind":"symbol","type":"topic","navigatorTitle":[{"kind":"identifier","text":"ConnectorProvisioningConfig"}],"url":"\/documentation\/awsappflow\/appflowclienttypes\/connectorprovisioningconfig"},"doc://AWSAppflow/documentation/AWSAppflow/AppflowClientTypes/TriggerType":{"role":"symbol","title":"AppflowClientTypes.TriggerType","fragments":[{"kind":"keyword","text":"enum"},{"kind":"text","text":" "},{"kind":"identifier","text":"TriggerType"}],"abstract":[],"identifier":"doc:\/\/AWSAppflow\/documentation\/AWSAppflow\/AppflowClientTypes\/TriggerType","kind":"symbol","type":"topic","navigatorTitle":[{"kind":"identifier","text":"TriggerType"}],"url":"\/documentation\/awsappflow\/appflowclienttypes\/triggertype"},"doc://AWSAppflow/documentation/AWSAppflow/AppflowClientTypes/AuthenticationConfig":{"role":"symbol","title":"AppflowClientTypes.AuthenticationConfig","fragments":[{"kind":"keyword","text":"struct"},{"kind":"text","text":" "},{"kind":"identifier","text":"AuthenticationConfig"}],"abstract":[{"type":"text","text":"Contains information about the authentication config that the connector supports."}],"identifier":"doc:\/\/AWSAppflow\/documentation\/AWSAppflow\/AppflowClientTypes\/AuthenticationConfig","kind":"symbol","type":"topic","navigatorTitle":[{"kind":"identifier","text":"AuthenticationConfig"}],"url":"\/documentation\/awsappflow\/appflowclienttypes\/authenticationconfig"},"doc://AWSAppflow/documentation/AWSAppflow/AppflowClientTypes/ConnectorProvisioningType":{"role":"symbol","title":"AppflowClientTypes.ConnectorProvisioningType","fragments":[{"kind":"keyword","text":"enum"},{"kind":"text","text":" "},{"kind":"identifier","text":"ConnectorProvisioningType"}],"abstract":[{"type":"text","text":"The type of provisioning that the connector supports, such as Lambda."}],"identifier":"doc:\/\/AWSAppflow\/documentation\/AWSAppflow\/AppflowClientTypes\/ConnectorProvisioningType","kind":"symbol","type":"topic","navigatorTitle":[{"kind":"identifier","text":"ConnectorProvisioningType"}],"url":"\/documentation\/awsappflow\/appflowclienttypes\/connectorprovisioningtype"},"doc://AWSAppflow/documentation/AWSAppflow/AppflowClientTypes/ConnectorMetadata":{"role":"symbol","title":"AppflowClientTypes.ConnectorMetadata","fragments":[{"kind":"keyword","text":"struct"},{"kind":"text","text":" "},{"kind":"identifier","text":"ConnectorMetadata"}],"abstract":[{"type":"text","text":"A structure to specify connector-specific metadata such as oAuthScopes, supportedRegions, privateLinkServiceUrl, and so on."}],"identifier":"doc:\/\/AWSAppflow\/documentation\/AWSAppflow\/AppflowClientTypes\/ConnectorMetadata","kind":"symbol","type":"topic","navigatorTitle":[{"kind":"identifier","text":"ConnectorMetadata"}],"url":"\/documentation\/awsappflow\/appflowclienttypes\/connectormetadata"},"doc://AWSAppflow/documentation/AWSAppflow/AppflowClientTypes/Operators":{"role":"symbol","title":"AppflowClientTypes.Operators","fragments":[{"kind":"keyword","text":"enum"},{"kind":"text","text":" "},{"kind":"identifier","text":"Operators"}],"abstract":[],"identifier":"doc:\/\/AWSAppflow\/documentation\/AWSAppflow\/AppflowClientTypes\/Operators","kind":"symbol","type":"topic","navigatorTitle":[{"kind":"identifier","text":"Operators"}],"url":"\/documentation\/awsappflow\/appflowclienttypes\/operators"},"doc://AWSAppflow/documentation/AWSAppflow/AppflowClientTypes/ScheduleFrequencyType":{"role":"symbol","title":"AppflowClientTypes.ScheduleFrequencyType","fragments":[{"kind":"keyword","text":"enum"},{"kind":"text","text":" "},{"kind":"identifier","text":"ScheduleFrequencyType"}],"abstract":[],"identifier":"doc:\/\/AWSAppflow\/documentation\/AWSAppflow\/AppflowClientTypes\/ScheduleFrequencyType","kind":"symbol","type":"topic","navigatorTitle":[{"kind":"identifier","text":"ScheduleFrequencyType"}],"url":"\/documentation\/awsappflow\/appflowclienttypes\/schedulefrequencytype"}}}