{"primaryContentSections":[{"kind":"declarations","declarations":[{"tokens":[{"kind":"keyword","text":"init"},{"kind":"text","text":"("},{"kind":"externalParam","text":"appId"},{"kind":"text","text":": "},{"kind":"typeIdentifier","text":"String","preciseIdentifier":"s:SS"},{"kind":"text","text":"? = nil, "},{"kind":"externalParam","text":"backendEnvironmentArn"},{"kind":"text","text":": "},{"kind":"typeIdentifier","text":"String","preciseIdentifier":"s:SS"},{"kind":"text","text":"? = nil, "},{"kind":"externalParam","text":"basicAuthCredentials"},{"kind":"text","text":": "},{"kind":"typeIdentifier","text":"String","preciseIdentifier":"s:SS"},{"kind":"text","text":"? = nil, "},{"kind":"externalParam","text":"branchName"},{"kind":"text","text":": "},{"kind":"typeIdentifier","text":"String","preciseIdentifier":"s:SS"},{"kind":"text","text":"? = nil, "},{"kind":"externalParam","text":"buildSpec"},{"kind":"text","text":": "},{"kind":"typeIdentifier","text":"String","preciseIdentifier":"s:SS"},{"kind":"text","text":"? = nil, "},{"kind":"externalParam","text":"description"},{"kind":"text","text":": "},{"kind":"typeIdentifier","text":"String","preciseIdentifier":"s:SS"},{"kind":"text","text":"? = nil, "},{"kind":"externalParam","text":"displayName"},{"kind":"text","text":": "},{"kind":"typeIdentifier","text":"String","preciseIdentifier":"s:SS"},{"kind":"text","text":"? = nil, "},{"kind":"externalParam","text":"enableAutoBuild"},{"kind":"text","text":": "},{"kind":"typeIdentifier","text":"Bool","preciseIdentifier":"s:Sb"},{"kind":"text","text":"? = nil, "},{"kind":"externalParam","text":"enableBasicAuth"},{"kind":"text","text":": "},{"kind":"typeIdentifier","text":"Bool","preciseIdentifier":"s:Sb"},{"kind":"text","text":"? = nil, "},{"kind":"externalParam","text":"enableNotification"},{"kind":"text","text":": "},{"kind":"typeIdentifier","text":"Bool","preciseIdentifier":"s:Sb"},{"kind":"text","text":"? = nil, "},{"kind":"externalParam","text":"enablePerformanceMode"},{"kind":"text","text":": "},{"kind":"typeIdentifier","text":"Bool","preciseIdentifier":"s:Sb"},{"kind":"text","text":"? = nil, "},{"kind":"externalParam","text":"enablePullRequestPreview"},{"kind":"text","text":": "},{"kind":"typeIdentifier","text":"Bool","preciseIdentifier":"s:Sb"},{"kind":"text","text":"? = nil, "},{"kind":"externalParam","text":"environmentVariables"},{"kind":"text","text":": ["},{"kind":"typeIdentifier","text":"String","preciseIdentifier":"s:SS"},{"kind":"text","text":" : "},{"kind":"typeIdentifier","text":"String","preciseIdentifier":"s:SS"},{"kind":"text","text":"]? = nil, "},{"kind":"externalParam","text":"framework"},{"kind":"text","text":": "},{"kind":"typeIdentifier","text":"String","preciseIdentifier":"s:SS"},{"kind":"text","text":"? = nil, "},{"kind":"externalParam","text":"pullRequestEnvironmentName"},{"kind":"text","text":": "},{"kind":"typeIdentifier","text":"String","preciseIdentifier":"s:SS"},{"kind":"text","text":"? = nil, "},{"kind":"externalParam","text":"stage"},{"kind":"text","text":": "},{"kind":"typeIdentifier","identifier":"doc:\/\/AWSAmplify\/documentation\/AWSAmplify\/AmplifyClientTypes","preciseIdentifier":"s:10AWSAmplify18AmplifyClientTypesO","text":"AmplifyClientTypes"},{"kind":"text","text":"."},{"kind":"typeIdentifier","identifier":"doc:\/\/AWSAmplify\/documentation\/AWSAmplify\/AmplifyClientTypes\/Stage","preciseIdentifier":"s:10AWSAmplify18AmplifyClientTypesO5StageO","text":"Stage"},{"kind":"text","text":"? = nil, "},{"kind":"externalParam","text":"ttl"},{"kind":"text","text":": "},{"kind":"typeIdentifier","text":"String","preciseIdentifier":"s:SS"},{"kind":"text","text":"? = nil)"}],"languages":["swift"],"platforms":["macOS"]}]}],"schemaVersion":{"major":0,"minor":3,"patch":0},"sections":[],"variants":[{"paths":["\/documentation\/awsamplify\/updatebranchinput\/init(appid:backendenvironmentarn:basicauthcredentials:branchname:buildspec:description:displayname:enableautobuild:enablebasicauth:enablenotification:enableperformancemode:enablepullrequestpreview:environmentvariables:framework:pullrequeste-3ellg"],"traits":[{"interfaceLanguage":"swift"}]}],"identifier":{"url":"doc:\/\/AWSAmplify\/documentation\/AWSAmplify\/UpdateBranchInput\/init(appId:backendEnvironmentArn:basicAuthCredentials:branchName:buildSpec:description:displayName:enableAutoBuild:enableBasicAuth:enableNotification:enablePerformanceMode:enablePullRequestPreview:environmentVariables:framework:pullRequestEnvironmentName:stage:ttl:)","interfaceLanguage":"swift"},"kind":"symbol","metadata":{"fragments":[{"kind":"identifier","text":"init"},{"kind":"text","text":"("},{"kind":"externalParam","text":"appId"},{"kind":"text","text":": "},{"kind":"typeIdentifier","text":"String","preciseIdentifier":"s:SS"},{"kind":"text","text":"?, "},{"kind":"externalParam","text":"backendEnvironmentArn"},{"kind":"text","text":": "},{"kind":"typeIdentifier","text":"String","preciseIdentifier":"s:SS"},{"kind":"text","text":"?, "},{"kind":"externalParam","text":"basicAuthCredentials"},{"kind":"text","text":": "},{"kind":"typeIdentifier","text":"String","preciseIdentifier":"s:SS"},{"kind":"text","text":"?, "},{"kind":"externalParam","text":"branchName"},{"kind":"text","text":": "},{"kind":"typeIdentifier","text":"String","preciseIdentifier":"s:SS"},{"kind":"text","text":"?, "},{"kind":"externalParam","text":"buildSpec"},{"kind":"text","text":": "},{"kind":"typeIdentifier","text":"String","preciseIdentifier":"s:SS"},{"kind":"text","text":"?, "},{"kind":"externalParam","text":"description"},{"kind":"text","text":": "},{"kind":"typeIdentifier","text":"String","preciseIdentifier":"s:SS"},{"kind":"text","text":"?, "},{"kind":"externalParam","text":"displayName"},{"kind":"text","text":": "},{"kind":"typeIdentifier","text":"String","preciseIdentifier":"s:SS"},{"kind":"text","text":"?, "},{"kind":"externalParam","text":"enableAutoBuild"},{"kind":"text","text":": "},{"kind":"typeIdentifier","text":"Bool","preciseIdentifier":"s:Sb"},{"kind":"text","text":"?, "},{"kind":"externalParam","text":"enableBasicAuth"},{"kind":"text","text":": "},{"kind":"typeIdentifier","text":"Bool","preciseIdentifier":"s:Sb"},{"kind":"text","text":"?, "},{"kind":"externalParam","text":"enableNotification"},{"kind":"text","text":": "},{"kind":"typeIdentifier","text":"Bool","preciseIdentifier":"s:Sb"},{"kind":"text","text":"?, "},{"kind":"externalParam","text":"enablePerformanceMode"},{"kind":"text","text":": "},{"kind":"typeIdentifier","text":"Bool","preciseIdentifier":"s:Sb"},{"kind":"text","text":"?, "},{"kind":"externalParam","text":"enablePullRequestPreview"},{"kind":"text","text":": "},{"kind":"typeIdentifier","text":"Bool","preciseIdentifier":"s:Sb"},{"kind":"text","text":"?, "},{"kind":"externalParam","text":"environmentVariables"},{"kind":"text","text":": ["},{"kind":"typeIdentifier","text":"String","preciseIdentifier":"s:SS"},{"kind":"text","text":" : "},{"kind":"typeIdentifier","text":"String","preciseIdentifier":"s:SS"},{"kind":"text","text":"]?, "},{"kind":"externalParam","text":"framework"},{"kind":"text","text":": "},{"kind":"typeIdentifier","text":"String","preciseIdentifier":"s:SS"},{"kind":"text","text":"?, "},{"kind":"externalParam","text":"pullRequestEnvironmentName"},{"kind":"text","text":": "},{"kind":"typeIdentifier","text":"String","preciseIdentifier":"s:SS"},{"kind":"text","text":"?, "},{"kind":"externalParam","text":"stage"},{"kind":"text","text":": "},{"kind":"typeIdentifier","text":"AmplifyClientTypes","preciseIdentifier":"s:10AWSAmplify18AmplifyClientTypesO"},{"kind":"text","text":"."},{"kind":"typeIdentifier","text":"Stage","preciseIdentifier":"s:10AWSAmplify18AmplifyClientTypesO5StageO"},{"kind":"text","text":"?, "},{"kind":"externalParam","text":"ttl"},{"kind":"text","text":": "},{"kind":"typeIdentifier","text":"String","preciseIdentifier":"s:SS"},{"kind":"text","text":"?)"}],"title":"init(appId:backendEnvironmentArn:basicAuthCredentials:branchName:buildSpec:description:displayName:enableAutoBuild:enableBasicAuth:enableNotification:enablePerformanceMode:enablePullRequestPreview:environmentVariables:framework:pullRequestEnvironmentName:stage:ttl:)","roleHeading":"Initializer","role":"symbol","symbolKind":"init","externalID":"s:10AWSAmplify17UpdateBranchInputV5appId21backendEnvironmentArn20basicAuthCredentials10branchName9buildSpec11description07displayN015enableAutoBuild0s5BasicK00S12Notification0S15PerformanceMode0S18PullRequestPreview20environmentVariables9framework011pullRequesthN05stage3ttlACSSSg_A6USbSgA4VSDyS2SGSgA2uA18AmplifyClientTypesO5StageOSgAUtcfc","modules":[{"name":"AWSAmplify"}]},"hierarchy":{"paths":[["doc:\/\/AWSAmplify\/documentation\/AWSAmplify","doc:\/\/AWSAmplify\/documentation\/AWSAmplify\/UpdateBranchInput"]]},"references":{"doc://AWSAmplify/documentation/AWSAmplify/UpdateBranchInput":{"role":"symbol","title":"UpdateBranchInput","fragments":[{"kind":"keyword","text":"struct"},{"kind":"text","text":" "},{"kind":"identifier","text":"UpdateBranchInput"}],"abstract":[{"type":"text","text":"The request structure for the update branch request."}],"identifier":"doc:\/\/AWSAmplify\/documentation\/AWSAmplify\/UpdateBranchInput","kind":"symbol","type":"topic","navigatorTitle":[{"kind":"identifier","text":"UpdateBranchInput"}],"url":"\/documentation\/awsamplify\/updatebranchinput"},"doc://AWSAmplify/documentation/AWSAmplify/AmplifyClientTypes/Stage":{"role":"symbol","title":"AmplifyClientTypes.Stage","fragments":[{"kind":"keyword","text":"enum"},{"kind":"text","text":" "},{"kind":"identifier","text":"Stage"}],"abstract":[],"identifier":"doc:\/\/AWSAmplify\/documentation\/AWSAmplify\/AmplifyClientTypes\/Stage","kind":"symbol","type":"topic","navigatorTitle":[{"kind":"identifier","text":"Stage"}],"url":"\/documentation\/awsamplify\/amplifyclienttypes\/stage"},"doc://AWSAmplify/documentation/AWSAmplify/AmplifyClientTypes":{"role":"symbol","title":"AmplifyClientTypes","fragments":[{"kind":"keyword","text":"enum"},{"kind":"text","text":" "},{"kind":"identifier","text":"AmplifyClientTypes"}],"abstract":[],"identifier":"doc:\/\/AWSAmplify\/documentation\/AWSAmplify\/AmplifyClientTypes","kind":"symbol","type":"topic","navigatorTitle":[{"kind":"identifier","text":"AmplifyClientTypes"}],"url":"\/documentation\/awsamplify\/amplifyclienttypes"},"doc://AWSAmplify/documentation/AWSAmplify/UpdateBranchInput/init(appId:backendEnvironmentArn:basicAuthCredentials:branchName:buildSpec:description:displayName:enableAutoBuild:enableBasicAuth:enableNotification:enablePerformanceMode:enablePullRequestPreview:environmentVariables:framework:pullRequestEnvironmentName:stage:ttl:)":{"role":"symbol","title":"init(appId:backendEnvironmentArn:basicAuthCredentials:branchName:buildSpec:description:displayName:enableAutoBuild:enableBasicAuth:enableNotification:enablePerformanceMode:enablePullRequestPreview:environmentVariables:framework:pullRequestEnvironmentName:stage:ttl:)","fragments":[{"kind":"identifier","text":"init"},{"kind":"text","text":"("},{"kind":"externalParam","text":"appId"},{"kind":"text","text":": "},{"kind":"typeIdentifier","text":"String","preciseIdentifier":"s:SS"},{"kind":"text","text":"?, "},{"kind":"externalParam","text":"backendEnvironmentArn"},{"kind":"text","text":": "},{"kind":"typeIdentifier","text":"String","preciseIdentifier":"s:SS"},{"kind":"text","text":"?, "},{"kind":"externalParam","text":"basicAuthCredentials"},{"kind":"text","text":": "},{"kind":"typeIdentifier","text":"String","preciseIdentifier":"s:SS"},{"kind":"text","text":"?, "},{"kind":"externalParam","text":"branchName"},{"kind":"text","text":": "},{"kind":"typeIdentifier","text":"String","preciseIdentifier":"s:SS"},{"kind":"text","text":"?, "},{"kind":"externalParam","text":"buildSpec"},{"kind":"text","text":": "},{"kind":"typeIdentifier","text":"String","preciseIdentifier":"s:SS"},{"kind":"text","text":"?, "},{"kind":"externalParam","text":"description"},{"kind":"text","text":": "},{"kind":"typeIdentifier","text":"String","preciseIdentifier":"s:SS"},{"kind":"text","text":"?, "},{"kind":"externalParam","text":"displayName"},{"kind":"text","text":": "},{"kind":"typeIdentifier","text":"String","preciseIdentifier":"s:SS"},{"kind":"text","text":"?, "},{"kind":"externalParam","text":"enableAutoBuild"},{"kind":"text","text":": "},{"kind":"typeIdentifier","text":"Bool","preciseIdentifier":"s:Sb"},{"kind":"text","text":"?, "},{"kind":"externalParam","text":"enableBasicAuth"},{"kind":"text","text":": "},{"kind":"typeIdentifier","text":"Bool","preciseIdentifier":"s:Sb"},{"kind":"text","text":"?, "},{"kind":"externalParam","text":"enableNotification"},{"kind":"text","text":": "},{"kind":"typeIdentifier","text":"Bool","preciseIdentifier":"s:Sb"},{"kind":"text","text":"?, "},{"kind":"externalParam","text":"enablePerformanceMode"},{"kind":"text","text":": "},{"kind":"typeIdentifier","text":"Bool","preciseIdentifier":"s:Sb"},{"kind":"text","text":"?, "},{"kind":"externalParam","text":"enablePullRequestPreview"},{"kind":"text","text":": "},{"kind":"typeIdentifier","text":"Bool","preciseIdentifier":"s:Sb"},{"kind":"text","text":"?, "},{"kind":"externalParam","text":"environmentVariables"},{"kind":"text","text":": ["},{"kind":"typeIdentifier","text":"String","preciseIdentifier":"s:SS"},{"kind":"text","text":" : "},{"kind":"typeIdentifier","text":"String","preciseIdentifier":"s:SS"},{"kind":"text","text":"]?, "},{"kind":"externalParam","text":"framework"},{"kind":"text","text":": "},{"kind":"typeIdentifier","text":"String","preciseIdentifier":"s:SS"},{"kind":"text","text":"?, "},{"kind":"externalParam","text":"pullRequestEnvironmentName"},{"kind":"text","text":": "},{"kind":"typeIdentifier","text":"String","preciseIdentifier":"s:SS"},{"kind":"text","text":"?, "},{"kind":"externalParam","text":"stage"},{"kind":"text","text":": "},{"kind":"typeIdentifier","text":"AmplifyClientTypes","preciseIdentifier":"s:10AWSAmplify18AmplifyClientTypesO"},{"kind":"text","text":"."},{"kind":"typeIdentifier","text":"Stage","preciseIdentifier":"s:10AWSAmplify18AmplifyClientTypesO5StageO"},{"kind":"text","text":"?, "},{"kind":"externalParam","text":"ttl"},{"kind":"text","text":": "},{"kind":"typeIdentifier","text":"String","preciseIdentifier":"s:SS"},{"kind":"text","text":"?)"}],"abstract":[],"identifier":"doc:\/\/AWSAmplify\/documentation\/AWSAmplify\/UpdateBranchInput\/init(appId:backendEnvironmentArn:basicAuthCredentials:branchName:buildSpec:description:displayName:enableAutoBuild:enableBasicAuth:enableNotification:enablePerformanceMode:enablePullRequestPreview:environmentVariables:framework:pullRequestEnvironmentName:stage:ttl:)","kind":"symbol","type":"topic","url":"\/documentation\/awsamplify\/updatebranchinput\/init(appid:backendenvironmentarn:basicauthcredentials:branchname:buildspec:description:displayname:enableautobuild:enablebasicauth:enablenotification:enableperformancemode:enablepullrequestpreview:environmentvariables:framework:pullrequeste-3ellg"},"doc://AWSAmplify/documentation/AWSAmplify":{"role":"collection","title":"AWSAmplify","abstract":[],"identifier":"doc:\/\/AWSAmplify\/documentation\/AWSAmplify","kind":"symbol","type":"topic","url":"\/documentation\/awsamplify"}}}