{"variants":[{"paths":["\/documentation\/awsapigatewayv2\/apigatewayv2client\/apigatewayv2clientprotocol-implementations"],"traits":[{"interfaceLanguage":"swift"}]}],"schemaVersion":{"major":0,"minor":3,"patch":0},"sections":[],"identifier":{"url":"doc:\/\/AWSApiGatewayV2\/documentation\/AWSApiGatewayV2\/ApiGatewayV2Client\/ApiGatewayV2ClientProtocol-Implementations","interfaceLanguage":"swift"},"topicSections":[{"title":"Instance Methods","identifiers":["doc:\/\/AWSApiGatewayV2\/documentation\/AWSApiGatewayV2\/ApiGatewayV2Client\/createApi(input:)","doc:\/\/AWSApiGatewayV2\/documentation\/AWSApiGatewayV2\/ApiGatewayV2Client\/createApiMapping(input:)","doc:\/\/AWSApiGatewayV2\/documentation\/AWSApiGatewayV2\/ApiGatewayV2Client\/createAuthorizer(input:)","doc:\/\/AWSApiGatewayV2\/documentation\/AWSApiGatewayV2\/ApiGatewayV2Client\/createDeployment(input:)","doc:\/\/AWSApiGatewayV2\/documentation\/AWSApiGatewayV2\/ApiGatewayV2Client\/createDomainName(input:)","doc:\/\/AWSApiGatewayV2\/documentation\/AWSApiGatewayV2\/ApiGatewayV2Client\/createIntegration(input:)","doc:\/\/AWSApiGatewayV2\/documentation\/AWSApiGatewayV2\/ApiGatewayV2Client\/createIntegrationResponse(input:)","doc:\/\/AWSApiGatewayV2\/documentation\/AWSApiGatewayV2\/ApiGatewayV2Client\/createModel(input:)","doc:\/\/AWSApiGatewayV2\/documentation\/AWSApiGatewayV2\/ApiGatewayV2Client\/createRoute(input:)","doc:\/\/AWSApiGatewayV2\/documentation\/AWSApiGatewayV2\/ApiGatewayV2Client\/createRouteResponse(input:)","doc:\/\/AWSApiGatewayV2\/documentation\/AWSApiGatewayV2\/ApiGatewayV2Client\/createStage(input:)","doc:\/\/AWSApiGatewayV2\/documentation\/AWSApiGatewayV2\/ApiGatewayV2Client\/createVpcLink(input:)","doc:\/\/AWSApiGatewayV2\/documentation\/AWSApiGatewayV2\/ApiGatewayV2Client\/deleteAccessLogSettings(input:)","doc:\/\/AWSApiGatewayV2\/documentation\/AWSApiGatewayV2\/ApiGatewayV2Client\/deleteApi(input:)","doc:\/\/AWSApiGatewayV2\/documentation\/AWSApiGatewayV2\/ApiGatewayV2Client\/deleteApiMapping(input:)","doc:\/\/AWSApiGatewayV2\/documentation\/AWSApiGatewayV2\/ApiGatewayV2Client\/deleteAuthorizer(input:)","doc:\/\/AWSApiGatewayV2\/documentation\/AWSApiGatewayV2\/ApiGatewayV2Client\/deleteCorsConfiguration(input:)","doc:\/\/AWSApiGatewayV2\/documentation\/AWSApiGatewayV2\/ApiGatewayV2Client\/deleteDeployment(input:)","doc:\/\/AWSApiGatewayV2\/documentation\/AWSApiGatewayV2\/ApiGatewayV2Client\/deleteDomainName(input:)","doc:\/\/AWSApiGatewayV2\/documentation\/AWSApiGatewayV2\/ApiGatewayV2Client\/deleteIntegration(input:)","doc:\/\/AWSApiGatewayV2\/documentation\/AWSApiGatewayV2\/ApiGatewayV2Client\/deleteIntegrationResponse(input:)","doc:\/\/AWSApiGatewayV2\/documentation\/AWSApiGatewayV2\/ApiGatewayV2Client\/deleteModel(input:)","doc:\/\/AWSApiGatewayV2\/documentation\/AWSApiGatewayV2\/ApiGatewayV2Client\/deleteRoute(input:)","doc:\/\/AWSApiGatewayV2\/documentation\/AWSApiGatewayV2\/ApiGatewayV2Client\/deleteRouteRequestParameter(input:)","doc:\/\/AWSApiGatewayV2\/documentation\/AWSApiGatewayV2\/ApiGatewayV2Client\/deleteRouteResponse(input:)","doc:\/\/AWSApiGatewayV2\/documentation\/AWSApiGatewayV2\/ApiGatewayV2Client\/deleteRouteSettings(input:)","doc:\/\/AWSApiGatewayV2\/documentation\/AWSApiGatewayV2\/ApiGatewayV2Client\/deleteStage(input:)","doc:\/\/AWSApiGatewayV2\/documentation\/AWSApiGatewayV2\/ApiGatewayV2Client\/deleteVpcLink(input:)","doc:\/\/AWSApiGatewayV2\/documentation\/AWSApiGatewayV2\/ApiGatewayV2Client\/exportApi(input:)","doc:\/\/AWSApiGatewayV2\/documentation\/AWSApiGatewayV2\/ApiGatewayV2Client\/getApi(input:)","doc:\/\/AWSApiGatewayV2\/documentation\/AWSApiGatewayV2\/ApiGatewayV2Client\/getApiMapping(input:)","doc:\/\/AWSApiGatewayV2\/documentation\/AWSApiGatewayV2\/ApiGatewayV2Client\/getApiMappings(input:)","doc:\/\/AWSApiGatewayV2\/documentation\/AWSApiGatewayV2\/ApiGatewayV2Client\/getApis(input:)","doc:\/\/AWSApiGatewayV2\/documentation\/AWSApiGatewayV2\/ApiGatewayV2Client\/getAuthorizer(input:)","doc:\/\/AWSApiGatewayV2\/documentation\/AWSApiGatewayV2\/ApiGatewayV2Client\/getAuthorizers(input:)","doc:\/\/AWSApiGatewayV2\/documentation\/AWSApiGatewayV2\/ApiGatewayV2Client\/getDeployment(input:)","doc:\/\/AWSApiGatewayV2\/documentation\/AWSApiGatewayV2\/ApiGatewayV2Client\/getDeployments(input:)","doc:\/\/AWSApiGatewayV2\/documentation\/AWSApiGatewayV2\/ApiGatewayV2Client\/getDomainName(input:)","doc:\/\/AWSApiGatewayV2\/documentation\/AWSApiGatewayV2\/ApiGatewayV2Client\/getDomainNames(input:)","doc:\/\/AWSApiGatewayV2\/documentation\/AWSApiGatewayV2\/ApiGatewayV2Client\/getIntegration(input:)","doc:\/\/AWSApiGatewayV2\/documentation\/AWSApiGatewayV2\/ApiGatewayV2Client\/getIntegrationResponse(input:)","doc:\/\/AWSApiGatewayV2\/documentation\/AWSApiGatewayV2\/ApiGatewayV2Client\/getIntegrationResponses(input:)","doc:\/\/AWSApiGatewayV2\/documentation\/AWSApiGatewayV2\/ApiGatewayV2Client\/getIntegrations(input:)","doc:\/\/AWSApiGatewayV2\/documentation\/AWSApiGatewayV2\/ApiGatewayV2Client\/getModel(input:)","doc:\/\/AWSApiGatewayV2\/documentation\/AWSApiGatewayV2\/ApiGatewayV2Client\/getModelTemplate(input:)","doc:\/\/AWSApiGatewayV2\/documentation\/AWSApiGatewayV2\/ApiGatewayV2Client\/getModels(input:)","doc:\/\/AWSApiGatewayV2\/documentation\/AWSApiGatewayV2\/ApiGatewayV2Client\/getRoute(input:)","doc:\/\/AWSApiGatewayV2\/documentation\/AWSApiGatewayV2\/ApiGatewayV2Client\/getRouteResponse(input:)","doc:\/\/AWSApiGatewayV2\/documentation\/AWSApiGatewayV2\/ApiGatewayV2Client\/getRouteResponses(input:)","doc:\/\/AWSApiGatewayV2\/documentation\/AWSApiGatewayV2\/ApiGatewayV2Client\/getRoutes(input:)","doc:\/\/AWSApiGatewayV2\/documentation\/AWSApiGatewayV2\/ApiGatewayV2Client\/getStage(input:)","doc:\/\/AWSApiGatewayV2\/documentation\/AWSApiGatewayV2\/ApiGatewayV2Client\/getStages(input:)","doc:\/\/AWSApiGatewayV2\/documentation\/AWSApiGatewayV2\/ApiGatewayV2Client\/getTags(input:)","doc:\/\/AWSApiGatewayV2\/documentation\/AWSApiGatewayV2\/ApiGatewayV2Client\/getVpcLink(input:)","doc:\/\/AWSApiGatewayV2\/documentation\/AWSApiGatewayV2\/ApiGatewayV2Client\/getVpcLinks(input:)","doc:\/\/AWSApiGatewayV2\/documentation\/AWSApiGatewayV2\/ApiGatewayV2Client\/importApi(input:)","doc:\/\/AWSApiGatewayV2\/documentation\/AWSApiGatewayV2\/ApiGatewayV2Client\/reimportApi(input:)","doc:\/\/AWSApiGatewayV2\/documentation\/AWSApiGatewayV2\/ApiGatewayV2Client\/resetAuthorizersCache(input:)","doc:\/\/AWSApiGatewayV2\/documentation\/AWSApiGatewayV2\/ApiGatewayV2Client\/tagResource(input:)","doc:\/\/AWSApiGatewayV2\/documentation\/AWSApiGatewayV2\/ApiGatewayV2Client\/untagResource(input:)","doc:\/\/AWSApiGatewayV2\/documentation\/AWSApiGatewayV2\/ApiGatewayV2Client\/updateApi(input:)","doc:\/\/AWSApiGatewayV2\/documentation\/AWSApiGatewayV2\/ApiGatewayV2Client\/updateApiMapping(input:)","doc:\/\/AWSApiGatewayV2\/documentation\/AWSApiGatewayV2\/ApiGatewayV2Client\/updateAuthorizer(input:)","doc:\/\/AWSApiGatewayV2\/documentation\/AWSApiGatewayV2\/ApiGatewayV2Client\/updateDeployment(input:)","doc:\/\/AWSApiGatewayV2\/documentation\/AWSApiGatewayV2\/ApiGatewayV2Client\/updateDomainName(input:)","doc:\/\/AWSApiGatewayV2\/documentation\/AWSApiGatewayV2\/ApiGatewayV2Client\/updateIntegration(input:)","doc:\/\/AWSApiGatewayV2\/documentation\/AWSApiGatewayV2\/ApiGatewayV2Client\/updateIntegrationResponse(input:)","doc:\/\/AWSApiGatewayV2\/documentation\/AWSApiGatewayV2\/ApiGatewayV2Client\/updateModel(input:)","doc:\/\/AWSApiGatewayV2\/documentation\/AWSApiGatewayV2\/ApiGatewayV2Client\/updateRoute(input:)","doc:\/\/AWSApiGatewayV2\/documentation\/AWSApiGatewayV2\/ApiGatewayV2Client\/updateRouteResponse(input:)","doc:\/\/AWSApiGatewayV2\/documentation\/AWSApiGatewayV2\/ApiGatewayV2Client\/updateStage(input:)","doc:\/\/AWSApiGatewayV2\/documentation\/AWSApiGatewayV2\/ApiGatewayV2Client\/updateVpcLink(input:)"],"generated":true}],"kind":"article","metadata":{"modules":[{"name":"AWSApiGatewayV2"}],"role":"collectionGroup","title":"ApiGatewayV2ClientProtocol Implementations"},"hierarchy":{"paths":[["doc:\/\/AWSApiGatewayV2\/documentation\/AWSApiGatewayV2","doc:\/\/AWSApiGatewayV2\/documentation\/AWSApiGatewayV2\/ApiGatewayV2Client"]]},"references":{"doc://AWSApiGatewayV2/documentation/AWSApiGatewayV2/ApiGatewayV2Client/deleteIntegration(input:)":{"role":"symbol","title":"deleteIntegration(input:)","fragments":[{"kind":"keyword","text":"func"},{"kind":"text","text":" "},{"kind":"identifier","text":"deleteIntegration"},{"kind":"text","text":"("},{"kind":"externalParam","text":"input"},{"kind":"text","text":": "},{"kind":"typeIdentifier","text":"DeleteIntegrationInput","preciseIdentifier":"s:15AWSApiGatewayV222DeleteIntegrationInputV"},{"kind":"text","text":") "},{"kind":"keyword","text":"async"},{"kind":"text","text":" "},{"kind":"keyword","text":"throws"},{"kind":"text","text":" -> "},{"kind":"typeIdentifier","text":"DeleteIntegrationOutputResponse","preciseIdentifier":"s:15AWSApiGatewayV231DeleteIntegrationOutputResponseV"}],"abstract":[{"type":"text","text":"Deletes an Integration."}],"identifier":"doc:\/\/AWSApiGatewayV2\/documentation\/AWSApiGatewayV2\/ApiGatewayV2Client\/deleteIntegration(input:)","kind":"symbol","type":"topic","url":"\/documentation\/awsapigatewayv2\/apigatewayv2client\/deleteintegration(input:)"},"doc://AWSApiGatewayV2/documentation/AWSApiGatewayV2/ApiGatewayV2Client/untagResource(input:)":{"role":"symbol","title":"untagResource(input:)","fragments":[{"kind":"keyword","text":"func"},{"kind":"text","text":" "},{"kind":"identifier","text":"untagResource"},{"kind":"text","text":"("},{"kind":"externalParam","text":"input"},{"kind":"text","text":": "},{"kind":"typeIdentifier","text":"UntagResourceInput","preciseIdentifier":"s:15AWSApiGatewayV218UntagResourceInputV"},{"kind":"text","text":") "},{"kind":"keyword","text":"async"},{"kind":"text","text":" "},{"kind":"keyword","text":"throws"},{"kind":"text","text":" -> "},{"kind":"typeIdentifier","text":"UntagResourceOutputResponse","preciseIdentifier":"s:15AWSApiGatewayV227UntagResourceOutputResponseV"}],"abstract":[{"type":"text","text":"Deletes a Tag."}],"identifier":"doc:\/\/AWSApiGatewayV2\/documentation\/AWSApiGatewayV2\/ApiGatewayV2Client\/untagResource(input:)","kind":"symbol","type":"topic","url":"\/documentation\/awsapigatewayv2\/apigatewayv2client\/untagresource(input:)"},"doc://AWSApiGatewayV2/documentation/AWSApiGatewayV2/ApiGatewayV2Client/deleteAccessLogSettings(input:)":{"role":"symbol","title":"deleteAccessLogSettings(input:)","fragments":[{"kind":"keyword","text":"func"},{"kind":"text","text":" "},{"kind":"identifier","text":"deleteAccessLogSettings"},{"kind":"text","text":"("},{"kind":"externalParam","text":"input"},{"kind":"text","text":": "},{"kind":"typeIdentifier","text":"DeleteAccessLogSettingsInput","preciseIdentifier":"s:15AWSApiGatewayV228DeleteAccessLogSettingsInputV"},{"kind":"text","text":") "},{"kind":"keyword","text":"async"},{"kind":"text","text":" "},{"kind":"keyword","text":"throws"},{"kind":"text","text":" -> "},{"kind":"typeIdentifier","text":"DeleteAccessLogSettingsOutputResponse","preciseIdentifier":"s:15AWSApiGatewayV237DeleteAccessLogSettingsOutputResponseV"}],"abstract":[{"type":"text","text":"Deletes the AccessLogSettings for a Stage. To disable access logging for a Stage, delete its AccessLogSettings."}],"identifier":"doc:\/\/AWSApiGatewayV2\/documentation\/AWSApiGatewayV2\/ApiGatewayV2Client\/deleteAccessLogSettings(input:)","kind":"symbol","type":"topic","url":"\/documentation\/awsapigatewayv2\/apigatewayv2client\/deleteaccesslogsettings(input:)"},"doc://AWSApiGatewayV2/documentation/AWSApiGatewayV2/ApiGatewayV2Client/getModel(input:)":{"role":"symbol","title":"getModel(input:)","fragments":[{"kind":"keyword","text":"func"},{"kind":"text","text":" "},{"kind":"identifier","text":"getModel"},{"kind":"text","text":"("},{"kind":"externalParam","text":"input"},{"kind":"text","text":": "},{"kind":"typeIdentifier","text":"GetModelInput","preciseIdentifier":"s:15AWSApiGatewayV213GetModelInputV"},{"kind":"text","text":") "},{"kind":"keyword","text":"async"},{"kind":"text","text":" "},{"kind":"keyword","text":"throws"},{"kind":"text","text":" -> "},{"kind":"typeIdentifier","text":"GetModelOutputResponse","preciseIdentifier":"s:15AWSApiGatewayV222GetModelOutputResponseV"}],"abstract":[{"type":"text","text":"Gets a Model."}],"identifier":"doc:\/\/AWSApiGatewayV2\/documentation\/AWSApiGatewayV2\/ApiGatewayV2Client\/getModel(input:)","kind":"symbol","type":"topic","url":"\/documentation\/awsapigatewayv2\/apigatewayv2client\/getmodel(input:)"},"doc://AWSApiGatewayV2/documentation/AWSApiGatewayV2":{"role":"collection","title":"AWSApiGatewayV2","abstract":[],"identifier":"doc:\/\/AWSApiGatewayV2\/documentation\/AWSApiGatewayV2","kind":"symbol","type":"topic","url":"\/documentation\/awsapigatewayv2"},"doc://AWSApiGatewayV2/documentation/AWSApiGatewayV2/ApiGatewayV2Client/getModelTemplate(input:)":{"role":"symbol","title":"getModelTemplate(input:)","fragments":[{"kind":"keyword","text":"func"},{"kind":"text","text":" "},{"kind":"identifier","text":"getModelTemplate"},{"kind":"text","text":"("},{"kind":"externalParam","text":"input"},{"kind":"text","text":": "},{"kind":"typeIdentifier","text":"GetModelTemplateInput","preciseIdentifier":"s:15AWSApiGatewayV221GetModelTemplateInputV"},{"kind":"text","text":") "},{"kind":"keyword","text":"async"},{"kind":"text","text":" "},{"kind":"keyword","text":"throws"},{"kind":"text","text":" -> "},{"kind":"typeIdentifier","text":"GetModelTemplateOutputResponse","preciseIdentifier":"s:15AWSApiGatewayV230GetModelTemplateOutputResponseV"}],"abstract":[{"type":"text","text":"Gets a model template."}],"identifier":"doc:\/\/AWSApiGatewayV2\/documentation\/AWSApiGatewayV2\/ApiGatewayV2Client\/getModelTemplate(input:)","kind":"symbol","type":"topic","url":"\/documentation\/awsapigatewayv2\/apigatewayv2client\/getmodeltemplate(input:)"},"doc://AWSApiGatewayV2/documentation/AWSApiGatewayV2/ApiGatewayV2Client/getTags(input:)":{"role":"symbol","title":"getTags(input:)","fragments":[{"kind":"keyword","text":"func"},{"kind":"text","text":" "},{"kind":"identifier","text":"getTags"},{"kind":"text","text":"("},{"kind":"externalParam","text":"input"},{"kind":"text","text":": "},{"kind":"typeIdentifier","text":"GetTagsInput","preciseIdentifier":"s:15AWSApiGatewayV212GetTagsInputV"},{"kind":"text","text":") "},{"kind":"keyword","text":"async"},{"kind":"text","text":" "},{"kind":"keyword","text":"throws"},{"kind":"text","text":" -> "},{"kind":"typeIdentifier","text":"GetTagsOutputResponse","preciseIdentifier":"s:15AWSApiGatewayV221GetTagsOutputResponseV"}],"abstract":[{"type":"text","text":"Gets a collection of Tag resources."}],"identifier":"doc:\/\/AWSApiGatewayV2\/documentation\/AWSApiGatewayV2\/ApiGatewayV2Client\/getTags(input:)","kind":"symbol","type":"topic","url":"\/documentation\/awsapigatewayv2\/apigatewayv2client\/gettags(input:)"},"doc://AWSApiGatewayV2/documentation/AWSApiGatewayV2/ApiGatewayV2Client/updateRouteResponse(input:)":{"role":"symbol","title":"updateRouteResponse(input:)","fragments":[{"kind":"keyword","text":"func"},{"kind":"text","text":" "},{"kind":"identifier","text":"updateRouteResponse"},{"kind":"text","text":"("},{"kind":"externalParam","text":"input"},{"kind":"text","text":": "},{"kind":"typeIdentifier","text":"UpdateRouteResponseInput","preciseIdentifier":"s:15AWSApiGatewayV224UpdateRouteResponseInputV"},{"kind":"text","text":") "},{"kind":"keyword","text":"async"},{"kind":"text","text":" "},{"kind":"keyword","text":"throws"},{"kind":"text","text":" -> "},{"kind":"typeIdentifier","text":"UpdateRouteResponseOutputResponse","preciseIdentifier":"s:15AWSApiGatewayV2025UpdateRouteResponseOutputF0V"}],"abstract":[{"type":"text","text":"Updates a RouteResponse."}],"identifier":"doc:\/\/AWSApiGatewayV2\/documentation\/AWSApiGatewayV2\/ApiGatewayV2Client\/updateRouteResponse(input:)","kind":"symbol","type":"topic","url":"\/documentation\/awsapigatewayv2\/apigatewayv2client\/updaterouteresponse(input:)"},"doc://AWSApiGatewayV2/documentation/AWSApiGatewayV2/ApiGatewayV2Client/deleteRoute(input:)":{"role":"symbol","title":"deleteRoute(input:)","fragments":[{"kind":"keyword","text":"func"},{"kind":"text","text":" "},{"kind":"identifier","text":"deleteRoute"},{"kind":"text","text":"("},{"kind":"externalParam","text":"input"},{"kind":"text","text":": "},{"kind":"typeIdentifier","text":"DeleteRouteInput","preciseIdentifier":"s:15AWSApiGatewayV216DeleteRouteInputV"},{"kind":"text","text":") "},{"kind":"keyword","text":"async"},{"kind":"text","text":" "},{"kind":"keyword","text":"throws"},{"kind":"text","text":" -> "},{"kind":"typeIdentifier","text":"DeleteRouteOutputResponse","preciseIdentifier":"s:15AWSApiGatewayV225DeleteRouteOutputResponseV"}],"abstract":[{"type":"text","text":"Deletes a Route."}],"identifier":"doc:\/\/AWSApiGatewayV2\/documentation\/AWSApiGatewayV2\/ApiGatewayV2Client\/deleteRoute(input:)","kind":"symbol","type":"topic","url":"\/documentation\/awsapigatewayv2\/apigatewayv2client\/deleteroute(input:)"},"doc://AWSApiGatewayV2/documentation/AWSApiGatewayV2/ApiGatewayV2Client/getApiMappings(input:)":{"role":"symbol","title":"getApiMappings(input:)","fragments":[{"kind":"keyword","text":"func"},{"kind":"text","text":" "},{"kind":"identifier","text":"getApiMappings"},{"kind":"text","text":"("},{"kind":"externalParam","text":"input"},{"kind":"text","text":": "},{"kind":"typeIdentifier","text":"GetApiMappingsInput","preciseIdentifier":"s:15AWSApiGatewayV219GetApiMappingsInputV"},{"kind":"text","text":") "},{"kind":"keyword","text":"async"},{"kind":"text","text":" "},{"kind":"keyword","text":"throws"},{"kind":"text","text":" -> "},{"kind":"typeIdentifier","text":"GetApiMappingsOutputResponse","preciseIdentifier":"s:15AWSApiGatewayV228GetApiMappingsOutputResponseV"}],"abstract":[{"type":"text","text":"Gets API mappings."}],"identifier":"doc:\/\/AWSApiGatewayV2\/documentation\/AWSApiGatewayV2\/ApiGatewayV2Client\/getApiMappings(input:)","kind":"symbol","type":"topic","url":"\/documentation\/awsapigatewayv2\/apigatewayv2client\/getapimappings(input:)"},"doc://AWSApiGatewayV2/documentation/AWSApiGatewayV2/ApiGatewayV2Client/getIntegration(input:)":{"role":"symbol","title":"getIntegration(input:)","fragments":[{"kind":"keyword","text":"func"},{"kind":"text","text":" "},{"kind":"identifier","text":"getIntegration"},{"kind":"text","text":"("},{"kind":"externalParam","text":"input"},{"kind":"text","text":": "},{"kind":"typeIdentifier","text":"GetIntegrationInput","preciseIdentifier":"s:15AWSApiGatewayV219GetIntegrationInputV"},{"kind":"text","text":") "},{"kind":"keyword","text":"async"},{"kind":"text","text":" "},{"kind":"keyword","text":"throws"},{"kind":"text","text":" -> "},{"kind":"typeIdentifier","text":"GetIntegrationOutputResponse","preciseIdentifier":"s:15AWSApiGatewayV228GetIntegrationOutputResponseV"}],"abstract":[{"type":"text","text":"Gets an Integration."}],"identifier":"doc:\/\/AWSApiGatewayV2\/documentation\/AWSApiGatewayV2\/ApiGatewayV2Client\/getIntegration(input:)","kind":"symbol","type":"topic","url":"\/documentation\/awsapigatewayv2\/apigatewayv2client\/getintegration(input:)"},"doc://AWSApiGatewayV2/documentation/AWSApiGatewayV2/ApiGatewayV2Client/getDomainName(input:)":{"role":"symbol","title":"getDomainName(input:)","fragments":[{"kind":"keyword","text":"func"},{"kind":"text","text":" "},{"kind":"identifier","text":"getDomainName"},{"kind":"text","text":"("},{"kind":"externalParam","text":"input"},{"kind":"text","text":": "},{"kind":"typeIdentifier","text":"GetDomainNameInput","preciseIdentifier":"s:15AWSApiGatewayV218GetDomainNameInputV"},{"kind":"text","text":") "},{"kind":"keyword","text":"async"},{"kind":"text","text":" "},{"kind":"keyword","text":"throws"},{"kind":"text","text":" -> "},{"kind":"typeIdentifier","text":"GetDomainNameOutputResponse","preciseIdentifier":"s:15AWSApiGatewayV227GetDomainNameOutputResponseV"}],"abstract":[{"type":"text","text":"Gets a domain name."}],"identifier":"doc:\/\/AWSApiGatewayV2\/documentation\/AWSApiGatewayV2\/ApiGatewayV2Client\/getDomainName(input:)","kind":"symbol","type":"topic","url":"\/documentation\/awsapigatewayv2\/apigatewayv2client\/getdomainname(input:)"},"doc://AWSApiGatewayV2/documentation/AWSApiGatewayV2/ApiGatewayV2Client/createDomainName(input:)":{"role":"symbol","title":"createDomainName(input:)","fragments":[{"kind":"keyword","text":"func"},{"kind":"text","text":" "},{"kind":"identifier","text":"createDomainName"},{"kind":"text","text":"("},{"kind":"externalParam","text":"input"},{"kind":"text","text":": "},{"kind":"typeIdentifier","text":"CreateDomainNameInput","preciseIdentifier":"s:15AWSApiGatewayV221CreateDomainNameInputV"},{"kind":"text","text":") "},{"kind":"keyword","text":"async"},{"kind":"text","text":" "},{"kind":"keyword","text":"throws"},{"kind":"text","text":" -> "},{"kind":"typeIdentifier","text":"CreateDomainNameOutputResponse","preciseIdentifier":"s:15AWSApiGatewayV230CreateDomainNameOutputResponseV"}],"abstract":[{"type":"text","text":"Creates a domain name."}],"identifier":"doc:\/\/AWSApiGatewayV2\/documentation\/AWSApiGatewayV2\/ApiGatewayV2Client\/createDomainName(input:)","kind":"symbol","type":"topic","url":"\/documentation\/awsapigatewayv2\/apigatewayv2client\/createdomainname(input:)"},"doc://AWSApiGatewayV2/documentation/AWSApiGatewayV2/ApiGatewayV2Client/getRouteResponses(input:)":{"role":"symbol","title":"getRouteResponses(input:)","fragments":[{"kind":"keyword","text":"func"},{"kind":"text","text":" "},{"kind":"identifier","text":"getRouteResponses"},{"kind":"text","text":"("},{"kind":"externalParam","text":"input"},{"kind":"text","text":": "},{"kind":"typeIdentifier","text":"GetRouteResponsesInput","preciseIdentifier":"s:15AWSApiGatewayV222GetRouteResponsesInputV"},{"kind":"text","text":") "},{"kind":"keyword","text":"async"},{"kind":"text","text":" "},{"kind":"keyword","text":"throws"},{"kind":"text","text":" -> "},{"kind":"typeIdentifier","text":"GetRouteResponsesOutputResponse","preciseIdentifier":"s:15AWSApiGatewayV231GetRouteResponsesOutputResponseV"}],"abstract":[{"type":"text","text":"Gets the RouteResponses for a Route."}],"identifier":"doc:\/\/AWSApiGatewayV2\/documentation\/AWSApiGatewayV2\/ApiGatewayV2Client\/getRouteResponses(input:)","kind":"symbol","type":"topic","url":"\/documentation\/awsapigatewayv2\/apigatewayv2client\/getrouteresponses(input:)"},"doc://AWSApiGatewayV2/documentation/AWSApiGatewayV2/ApiGatewayV2Client/getDeployment(input:)":{"role":"symbol","title":"getDeployment(input:)","fragments":[{"kind":"keyword","text":"func"},{"kind":"text","text":" "},{"kind":"identifier","text":"getDeployment"},{"kind":"text","text":"("},{"kind":"externalParam","text":"input"},{"kind":"text","text":": "},{"kind":"typeIdentifier","text":"GetDeploymentInput","preciseIdentifier":"s:15AWSApiGatewayV218GetDeploymentInputV"},{"kind":"text","text":") "},{"kind":"keyword","text":"async"},{"kind":"text","text":" "},{"kind":"keyword","text":"throws"},{"kind":"text","text":" -> "},{"kind":"typeIdentifier","text":"GetDeploymentOutputResponse","preciseIdentifier":"s:15AWSApiGatewayV227GetDeploymentOutputResponseV"}],"abstract":[{"type":"text","text":"Gets a Deployment."}],"identifier":"doc:\/\/AWSApiGatewayV2\/documentation\/AWSApiGatewayV2\/ApiGatewayV2Client\/getDeployment(input:)","kind":"symbol","type":"topic","url":"\/documentation\/awsapigatewayv2\/apigatewayv2client\/getdeployment(input:)"},"doc://AWSApiGatewayV2/documentation/AWSApiGatewayV2/ApiGatewayV2Client/createVpcLink(input:)":{"role":"symbol","title":"createVpcLink(input:)","fragments":[{"kind":"keyword","text":"func"},{"kind":"text","text":" "},{"kind":"identifier","text":"createVpcLink"},{"kind":"text","text":"("},{"kind":"externalParam","text":"input"},{"kind":"text","text":": "},{"kind":"typeIdentifier","text":"CreateVpcLinkInput","preciseIdentifier":"s:15AWSApiGatewayV218CreateVpcLinkInputV"},{"kind":"text","text":") "},{"kind":"keyword","text":"async"},{"kind":"text","text":" "},{"kind":"keyword","text":"throws"},{"kind":"text","text":" -> "},{"kind":"typeIdentifier","text":"CreateVpcLinkOutputResponse","preciseIdentifier":"s:15AWSApiGatewayV227CreateVpcLinkOutputResponseV"}],"abstract":[{"type":"text","text":"Creates a VPC link."}],"identifier":"doc:\/\/AWSApiGatewayV2\/documentation\/AWSApiGatewayV2\/ApiGatewayV2Client\/createVpcLink(input:)","kind":"symbol","type":"topic","url":"\/documentation\/awsapigatewayv2\/apigatewayv2client\/createvpclink(input:)"},"doc://AWSApiGatewayV2/documentation/AWSApiGatewayV2/ApiGatewayV2Client/createIntegrationResponse(input:)":{"role":"symbol","title":"createIntegrationResponse(input:)","fragments":[{"kind":"keyword","text":"func"},{"kind":"text","text":" "},{"kind":"identifier","text":"createIntegrationResponse"},{"kind":"text","text":"("},{"kind":"externalParam","text":"input"},{"kind":"text","text":": "},{"kind":"typeIdentifier","text":"CreateIntegrationResponseInput","preciseIdentifier":"s:15AWSApiGatewayV230CreateIntegrationResponseInputV"},{"kind":"text","text":") "},{"kind":"keyword","text":"async"},{"kind":"text","text":" "},{"kind":"keyword","text":"throws"},{"kind":"text","text":" -> "},{"kind":"typeIdentifier","text":"CreateIntegrationResponseOutputResponse","preciseIdentifier":"s:15AWSApiGatewayV2031CreateIntegrationResponseOutputF0V"}],"abstract":[{"type":"text","text":"Creates an IntegrationResponses."}],"identifier":"doc:\/\/AWSApiGatewayV2\/documentation\/AWSApiGatewayV2\/ApiGatewayV2Client\/createIntegrationResponse(input:)","kind":"symbol","type":"topic","url":"\/documentation\/awsapigatewayv2\/apigatewayv2client\/createintegrationresponse(input:)"},"doc://AWSApiGatewayV2/documentation/AWSApiGatewayV2/ApiGatewayV2Client/updateVpcLink(input:)":{"role":"symbol","title":"updateVpcLink(input:)","fragments":[{"kind":"keyword","text":"func"},{"kind":"text","text":" "},{"kind":"identifier","text":"updateVpcLink"},{"kind":"text","text":"("},{"kind":"externalParam","text":"input"},{"kind":"text","text":": "},{"kind":"typeIdentifier","text":"UpdateVpcLinkInput","preciseIdentifier":"s:15AWSApiGatewayV218UpdateVpcLinkInputV"},{"kind":"text","text":") "},{"kind":"keyword","text":"async"},{"kind":"text","text":" "},{"kind":"keyword","text":"throws"},{"kind":"text","text":" -> "},{"kind":"typeIdentifier","text":"UpdateVpcLinkOutputResponse","preciseIdentifier":"s:15AWSApiGatewayV227UpdateVpcLinkOutputResponseV"}],"abstract":[{"type":"text","text":"Updates a VPC link."}],"identifier":"doc:\/\/AWSApiGatewayV2\/documentation\/AWSApiGatewayV2\/ApiGatewayV2Client\/updateVpcLink(input:)","kind":"symbol","type":"topic","url":"\/documentation\/awsapigatewayv2\/apigatewayv2client\/updatevpclink(input:)"},"doc://AWSApiGatewayV2/documentation/AWSApiGatewayV2/ApiGatewayV2Client/deleteDeployment(input:)":{"role":"symbol","title":"deleteDeployment(input:)","fragments":[{"kind":"keyword","text":"func"},{"kind":"text","text":" "},{"kind":"identifier","text":"deleteDeployment"},{"kind":"text","text":"("},{"kind":"externalParam","text":"input"},{"kind":"text","text":": "},{"kind":"typeIdentifier","text":"DeleteDeploymentInput","preciseIdentifier":"s:15AWSApiGatewayV221DeleteDeploymentInputV"},{"kind":"text","text":") "},{"kind":"keyword","text":"async"},{"kind":"text","text":" "},{"kind":"keyword","text":"throws"},{"kind":"text","text":" -> "},{"kind":"typeIdentifier","text":"DeleteDeploymentOutputResponse","preciseIdentifier":"s:15AWSApiGatewayV230DeleteDeploymentOutputResponseV"}],"abstract":[{"type":"text","text":"Deletes a Deployment."}],"identifier":"doc:\/\/AWSApiGatewayV2\/documentation\/AWSApiGatewayV2\/ApiGatewayV2Client\/deleteDeployment(input:)","kind":"symbol","type":"topic","url":"\/documentation\/awsapigatewayv2\/apigatewayv2client\/deletedeployment(input:)"},"doc://AWSApiGatewayV2/documentation/AWSApiGatewayV2/ApiGatewayV2Client/getStages(input:)":{"role":"symbol","title":"getStages(input:)","fragments":[{"kind":"keyword","text":"func"},{"kind":"text","text":" "},{"kind":"identifier","text":"getStages"},{"kind":"text","text":"("},{"kind":"externalParam","text":"input"},{"kind":"text","text":": "},{"kind":"typeIdentifier","text":"GetStagesInput","preciseIdentifier":"s:15AWSApiGatewayV214GetStagesInputV"},{"kind":"text","text":") "},{"kind":"keyword","text":"async"},{"kind":"text","text":" "},{"kind":"keyword","text":"throws"},{"kind":"text","text":" -> "},{"kind":"typeIdentifier","text":"GetStagesOutputResponse","preciseIdentifier":"s:15AWSApiGatewayV223GetStagesOutputResponseV"}],"abstract":[{"type":"text","text":"Gets the Stages for an API."}],"identifier":"doc:\/\/AWSApiGatewayV2\/documentation\/AWSApiGatewayV2\/ApiGatewayV2Client\/getStages(input:)","kind":"symbol","type":"topic","url":"\/documentation\/awsapigatewayv2\/apigatewayv2client\/getstages(input:)"},"doc://AWSApiGatewayV2/documentation/AWSApiGatewayV2/ApiGatewayV2Client/getRoutes(input:)":{"role":"symbol","title":"getRoutes(input:)","fragments":[{"kind":"keyword","text":"func"},{"kind":"text","text":" "},{"kind":"identifier","text":"getRoutes"},{"kind":"text","text":"("},{"kind":"externalParam","text":"input"},{"kind":"text","text":": "},{"kind":"typeIdentifier","text":"GetRoutesInput","preciseIdentifier":"s:15AWSApiGatewayV214GetRoutesInputV"},{"kind":"text","text":") "},{"kind":"keyword","text":"async"},{"kind":"text","text":" "},{"kind":"keyword","text":"throws"},{"kind":"text","text":" -> "},{"kind":"typeIdentifier","text":"GetRoutesOutputResponse","preciseIdentifier":"s:15AWSApiGatewayV223GetRoutesOutputResponseV"}],"abstract":[{"type":"text","text":"Gets the Routes for an API."}],"identifier":"doc:\/\/AWSApiGatewayV2\/documentation\/AWSApiGatewayV2\/ApiGatewayV2Client\/getRoutes(input:)","kind":"symbol","type":"topic","url":"\/documentation\/awsapigatewayv2\/apigatewayv2client\/getroutes(input:)"},"doc://AWSApiGatewayV2/documentation/AWSApiGatewayV2/ApiGatewayV2Client/exportApi(input:)":{"role":"symbol","title":"exportApi(input:)","fragments":[{"kind":"keyword","text":"func"},{"kind":"text","text":" "},{"kind":"identifier","text":"exportApi"},{"kind":"text","text":"("},{"kind":"externalParam","text":"input"},{"kind":"text","text":": "},{"kind":"typeIdentifier","text":"ExportApiInput","preciseIdentifier":"s:15AWSApiGatewayV214ExportApiInputV"},{"kind":"text","text":") "},{"kind":"keyword","text":"async"},{"kind":"text","text":" "},{"kind":"keyword","text":"throws"},{"kind":"text","text":" -> "},{"kind":"typeIdentifier","text":"ExportApiOutputResponse","preciseIdentifier":"s:15AWSApiGatewayV223ExportApiOutputResponseV"}],"abstract":[],"identifier":"doc:\/\/AWSApiGatewayV2\/documentation\/AWSApiGatewayV2\/ApiGatewayV2Client\/exportApi(input:)","kind":"symbol","type":"topic","url":"\/documentation\/awsapigatewayv2\/apigatewayv2client\/exportapi(input:)"},"doc://AWSApiGatewayV2/documentation/AWSApiGatewayV2/ApiGatewayV2Client/getDomainNames(input:)":{"role":"symbol","title":"getDomainNames(input:)","fragments":[{"kind":"keyword","text":"func"},{"kind":"text","text":" "},{"kind":"identifier","text":"getDomainNames"},{"kind":"text","text":"("},{"kind":"externalParam","text":"input"},{"kind":"text","text":": "},{"kind":"typeIdentifier","text":"GetDomainNamesInput","preciseIdentifier":"s:15AWSApiGatewayV219GetDomainNamesInputV"},{"kind":"text","text":") "},{"kind":"keyword","text":"async"},{"kind":"text","text":" "},{"kind":"keyword","text":"throws"},{"kind":"text","text":" -> "},{"kind":"typeIdentifier","text":"GetDomainNamesOutputResponse","preciseIdentifier":"s:15AWSApiGatewayV228GetDomainNamesOutputResponseV"}],"abstract":[{"type":"text","text":"Gets the domain names for an AWS account."}],"identifier":"doc:\/\/AWSApiGatewayV2\/documentation\/AWSApiGatewayV2\/ApiGatewayV2Client\/getDomainNames(input:)","kind":"symbol","type":"topic","url":"\/documentation\/awsapigatewayv2\/apigatewayv2client\/getdomainnames(input:)"},"doc://AWSApiGatewayV2/documentation/AWSApiGatewayV2/ApiGatewayV2Client/getAuthorizers(input:)":{"role":"symbol","title":"getAuthorizers(input:)","fragments":[{"kind":"keyword","text":"func"},{"kind":"text","text":" "},{"kind":"identifier","text":"getAuthorizers"},{"kind":"text","text":"("},{"kind":"externalParam","text":"input"},{"kind":"text","text":": "},{"kind":"typeIdentifier","text":"GetAuthorizersInput","preciseIdentifier":"s:15AWSApiGatewayV219GetAuthorizersInputV"},{"kind":"text","text":") "},{"kind":"keyword","text":"async"},{"kind":"text","text":" "},{"kind":"keyword","text":"throws"},{"kind":"text","text":" -> "},{"kind":"typeIdentifier","text":"GetAuthorizersOutputResponse","preciseIdentifier":"s:15AWSApiGatewayV228GetAuthorizersOutputResponseV"}],"abstract":[{"type":"text","text":"Gets the Authorizers for an API."}],"identifier":"doc:\/\/AWSApiGatewayV2\/documentation\/AWSApiGatewayV2\/ApiGatewayV2Client\/getAuthorizers(input:)","kind":"symbol","type":"topic","url":"\/documentation\/awsapigatewayv2\/apigatewayv2client\/getauthorizers(input:)"},"doc://AWSApiGatewayV2/documentation/AWSApiGatewayV2/ApiGatewayV2Client/deleteVpcLink(input:)":{"role":"symbol","title":"deleteVpcLink(input:)","fragments":[{"kind":"keyword","text":"func"},{"kind":"text","text":" "},{"kind":"identifier","text":"deleteVpcLink"},{"kind":"text","text":"("},{"kind":"externalParam","text":"input"},{"kind":"text","text":": "},{"kind":"typeIdentifier","text":"DeleteVpcLinkInput","preciseIdentifier":"s:15AWSApiGatewayV218DeleteVpcLinkInputV"},{"kind":"text","text":") "},{"kind":"keyword","text":"async"},{"kind":"text","text":" "},{"kind":"keyword","text":"throws"},{"kind":"text","text":" -> "},{"kind":"typeIdentifier","text":"DeleteVpcLinkOutputResponse","preciseIdentifier":"s:15AWSApiGatewayV227DeleteVpcLinkOutputResponseV"}],"abstract":[{"type":"text","text":"Deletes a VPC link."}],"identifier":"doc:\/\/AWSApiGatewayV2\/documentation\/AWSApiGatewayV2\/ApiGatewayV2Client\/deleteVpcLink(input:)","kind":"symbol","type":"topic","url":"\/documentation\/awsapigatewayv2\/apigatewayv2client\/deletevpclink(input:)"},"doc://AWSApiGatewayV2/documentation/AWSApiGatewayV2/ApiGatewayV2Client/getModels(input:)":{"role":"symbol","title":"getModels(input:)","fragments":[{"kind":"keyword","text":"func"},{"kind":"text","text":" "},{"kind":"identifier","text":"getModels"},{"kind":"text","text":"("},{"kind":"externalParam","text":"input"},{"kind":"text","text":": "},{"kind":"typeIdentifier","text":"GetModelsInput","preciseIdentifier":"s:15AWSApiGatewayV214GetModelsInputV"},{"kind":"text","text":") "},{"kind":"keyword","text":"async"},{"kind":"text","text":" "},{"kind":"keyword","text":"throws"},{"kind":"text","text":" -> "},{"kind":"typeIdentifier","text":"GetModelsOutputResponse","preciseIdentifier":"s:15AWSApiGatewayV223GetModelsOutputResponseV"}],"abstract":[{"type":"text","text":"Gets the Models for an API."}],"identifier":"doc:\/\/AWSApiGatewayV2\/documentation\/AWSApiGatewayV2\/ApiGatewayV2Client\/getModels(input:)","kind":"symbol","type":"topic","url":"\/documentation\/awsapigatewayv2\/apigatewayv2client\/getmodels(input:)"},"doc://AWSApiGatewayV2/documentation/AWSApiGatewayV2/ApiGatewayV2Client/reimportApi(input:)":{"role":"symbol","title":"reimportApi(input:)","fragments":[{"kind":"keyword","text":"func"},{"kind":"text","text":" "},{"kind":"identifier","text":"reimportApi"},{"kind":"text","text":"("},{"kind":"externalParam","text":"input"},{"kind":"text","text":": "},{"kind":"typeIdentifier","text":"ReimportApiInput","preciseIdentifier":"s:15AWSApiGatewayV216ReimportApiInputV"},{"kind":"text","text":") "},{"kind":"keyword","text":"async"},{"kind":"text","text":" "},{"kind":"keyword","text":"throws"},{"kind":"text","text":" -> "},{"kind":"typeIdentifier","text":"ReimportApiOutputResponse","preciseIdentifier":"s:15AWSApiGatewayV225ReimportApiOutputResponseV"}],"abstract":[{"type":"text","text":"Puts an Api resource."}],"identifier":"doc:\/\/AWSApiGatewayV2\/documentation\/AWSApiGatewayV2\/ApiGatewayV2Client\/reimportApi(input:)","kind":"symbol","type":"topic","url":"\/documentation\/awsapigatewayv2\/apigatewayv2client\/reimportapi(input:)"},"doc://AWSApiGatewayV2/documentation/AWSApiGatewayV2/ApiGatewayV2Client/deleteIntegrationResponse(input:)":{"role":"symbol","title":"deleteIntegrationResponse(input:)","fragments":[{"kind":"keyword","text":"func"},{"kind":"text","text":" "},{"kind":"identifier","text":"deleteIntegrationResponse"},{"kind":"text","text":"("},{"kind":"externalParam","text":"input"},{"kind":"text","text":": "},{"kind":"typeIdentifier","text":"DeleteIntegrationResponseInput","preciseIdentifier":"s:15AWSApiGatewayV230DeleteIntegrationResponseInputV"},{"kind":"text","text":") "},{"kind":"keyword","text":"async"},{"kind":"text","text":" "},{"kind":"keyword","text":"throws"},{"kind":"text","text":" -> "},{"kind":"typeIdentifier","text":"DeleteIntegrationResponseOutputResponse","preciseIdentifier":"s:15AWSApiGatewayV2031DeleteIntegrationResponseOutputF0V"}],"abstract":[{"type":"text","text":"Deletes an IntegrationResponses."}],"identifier":"doc:\/\/AWSApiGatewayV2\/documentation\/AWSApiGatewayV2\/ApiGatewayV2Client\/deleteIntegrationResponse(input:)","kind":"symbol","type":"topic","url":"\/documentation\/awsapigatewayv2\/apigatewayv2client\/deleteintegrationresponse(input:)"},"doc://AWSApiGatewayV2/documentation/AWSApiGatewayV2/ApiGatewayV2Client/tagResource(input:)":{"role":"symbol","title":"tagResource(input:)","fragments":[{"kind":"keyword","text":"func"},{"kind":"text","text":" "},{"kind":"identifier","text":"tagResource"},{"kind":"text","text":"("},{"kind":"externalParam","text":"input"},{"kind":"text","text":": "},{"kind":"typeIdentifier","text":"TagResourceInput","preciseIdentifier":"s:15AWSApiGatewayV216TagResourceInputV"},{"kind":"text","text":") "},{"kind":"keyword","text":"async"},{"kind":"text","text":" "},{"kind":"keyword","text":"throws"},{"kind":"text","text":" -> "},{"kind":"typeIdentifier","text":"TagResourceOutputResponse","preciseIdentifier":"s:15AWSApiGatewayV225TagResourceOutputResponseV"}],"abstract":[{"type":"text","text":"Creates a new Tag resource to represent a tag."}],"identifier":"doc:\/\/AWSApiGatewayV2\/documentation\/AWSApiGatewayV2\/ApiGatewayV2Client\/tagResource(input:)","kind":"symbol","type":"topic","url":"\/documentation\/awsapigatewayv2\/apigatewayv2client\/tagresource(input:)"},"doc://AWSApiGatewayV2/documentation/AWSApiGatewayV2/ApiGatewayV2Client/createApiMapping(input:)":{"role":"symbol","title":"createApiMapping(input:)","fragments":[{"kind":"keyword","text":"func"},{"kind":"text","text":" "},{"kind":"identifier","text":"createApiMapping"},{"kind":"text","text":"("},{"kind":"externalParam","text":"input"},{"kind":"text","text":": "},{"kind":"typeIdentifier","text":"CreateApiMappingInput","preciseIdentifier":"s:15AWSApiGatewayV221CreateApiMappingInputV"},{"kind":"text","text":") "},{"kind":"keyword","text":"async"},{"kind":"text","text":" "},{"kind":"keyword","text":"throws"},{"kind":"text","text":" -> "},{"kind":"typeIdentifier","text":"CreateApiMappingOutputResponse","preciseIdentifier":"s:15AWSApiGatewayV230CreateApiMappingOutputResponseV"}],"abstract":[{"type":"text","text":"Creates an API mapping."}],"identifier":"doc:\/\/AWSApiGatewayV2\/documentation\/AWSApiGatewayV2\/ApiGatewayV2Client\/createApiMapping(input:)","kind":"symbol","type":"topic","url":"\/documentation\/awsapigatewayv2\/apigatewayv2client\/createapimapping(input:)"},"doc://AWSApiGatewayV2/documentation/AWSApiGatewayV2/ApiGatewayV2Client/createRouteResponse(input:)":{"role":"symbol","title":"createRouteResponse(input:)","fragments":[{"kind":"keyword","text":"func"},{"kind":"text","text":" "},{"kind":"identifier","text":"createRouteResponse"},{"kind":"text","text":"("},{"kind":"externalParam","text":"input"},{"kind":"text","text":": "},{"kind":"typeIdentifier","text":"CreateRouteResponseInput","preciseIdentifier":"s:15AWSApiGatewayV224CreateRouteResponseInputV"},{"kind":"text","text":") "},{"kind":"keyword","text":"async"},{"kind":"text","text":" "},{"kind":"keyword","text":"throws"},{"kind":"text","text":" -> "},{"kind":"typeIdentifier","text":"CreateRouteResponseOutputResponse","preciseIdentifier":"s:15AWSApiGatewayV2025CreateRouteResponseOutputF0V"}],"abstract":[{"type":"text","text":"Creates a RouteResponse for a Route."}],"identifier":"doc:\/\/AWSApiGatewayV2\/documentation\/AWSApiGatewayV2\/ApiGatewayV2Client\/createRouteResponse(input:)","kind":"symbol","type":"topic","url":"\/documentation\/awsapigatewayv2\/apigatewayv2client\/createrouteresponse(input:)"},"doc://AWSApiGatewayV2/documentation/AWSApiGatewayV2/ApiGatewayV2Client/updateStage(input:)":{"role":"symbol","title":"updateStage(input:)","fragments":[{"kind":"keyword","text":"func"},{"kind":"text","text":" "},{"kind":"identifier","text":"updateStage"},{"kind":"text","text":"("},{"kind":"externalParam","text":"input"},{"kind":"text","text":": "},{"kind":"typeIdentifier","text":"UpdateStageInput","preciseIdentifier":"s:15AWSApiGatewayV216UpdateStageInputV"},{"kind":"text","text":") "},{"kind":"keyword","text":"async"},{"kind":"text","text":" "},{"kind":"keyword","text":"throws"},{"kind":"text","text":" -> "},{"kind":"typeIdentifier","text":"UpdateStageOutputResponse","preciseIdentifier":"s:15AWSApiGatewayV225UpdateStageOutputResponseV"}],"abstract":[{"type":"text","text":"Updates a Stage."}],"identifier":"doc:\/\/AWSApiGatewayV2\/documentation\/AWSApiGatewayV2\/ApiGatewayV2Client\/updateStage(input:)","kind":"symbol","type":"topic","url":"\/documentation\/awsapigatewayv2\/apigatewayv2client\/updatestage(input:)"},"doc://AWSApiGatewayV2/documentation/AWSApiGatewayV2/ApiGatewayV2Client/updateIntegrationResponse(input:)":{"role":"symbol","title":"updateIntegrationResponse(input:)","fragments":[{"kind":"keyword","text":"func"},{"kind":"text","text":" "},{"kind":"identifier","text":"updateIntegrationResponse"},{"kind":"text","text":"("},{"kind":"externalParam","text":"input"},{"kind":"text","text":": "},{"kind":"typeIdentifier","text":"UpdateIntegrationResponseInput","preciseIdentifier":"s:15AWSApiGatewayV230UpdateIntegrationResponseInputV"},{"kind":"text","text":") "},{"kind":"keyword","text":"async"},{"kind":"text","text":" "},{"kind":"keyword","text":"throws"},{"kind":"text","text":" -> "},{"kind":"typeIdentifier","text":"UpdateIntegrationResponseOutputResponse","preciseIdentifier":"s:15AWSApiGatewayV2031UpdateIntegrationResponseOutputF0V"}],"abstract":[{"type":"text","text":"Updates an IntegrationResponses."}],"identifier":"doc:\/\/AWSApiGatewayV2\/documentation\/AWSApiGatewayV2\/ApiGatewayV2Client\/updateIntegrationResponse(input:)","kind":"symbol","type":"topic","url":"\/documentation\/awsapigatewayv2\/apigatewayv2client\/updateintegrationresponse(input:)"},"doc://AWSApiGatewayV2/documentation/AWSApiGatewayV2/ApiGatewayV2Client/createAuthorizer(input:)":{"role":"symbol","title":"createAuthorizer(input:)","fragments":[{"kind":"keyword","text":"func"},{"kind":"text","text":" "},{"kind":"identifier","text":"createAuthorizer"},{"kind":"text","text":"("},{"kind":"externalParam","text":"input"},{"kind":"text","text":": "},{"kind":"typeIdentifier","text":"CreateAuthorizerInput","preciseIdentifier":"s:15AWSApiGatewayV221CreateAuthorizerInputV"},{"kind":"text","text":") "},{"kind":"keyword","text":"async"},{"kind":"text","text":" "},{"kind":"keyword","text":"throws"},{"kind":"text","text":" -> "},{"kind":"typeIdentifier","text":"CreateAuthorizerOutputResponse","preciseIdentifier":"s:15AWSApiGatewayV230CreateAuthorizerOutputResponseV"}],"abstract":[{"type":"text","text":"Creates an Authorizer for an API."}],"identifier":"doc:\/\/AWSApiGatewayV2\/documentation\/AWSApiGatewayV2\/ApiGatewayV2Client\/createAuthorizer(input:)","kind":"symbol","type":"topic","url":"\/documentation\/awsapigatewayv2\/apigatewayv2client\/createauthorizer(input:)"},"doc://AWSApiGatewayV2/documentation/AWSApiGatewayV2/ApiGatewayV2Client/deleteStage(input:)":{"role":"symbol","title":"deleteStage(input:)","fragments":[{"kind":"keyword","text":"func"},{"kind":"text","text":" "},{"kind":"identifier","text":"deleteStage"},{"kind":"text","text":"("},{"kind":"externalParam","text":"input"},{"kind":"text","text":": "},{"kind":"typeIdentifier","text":"DeleteStageInput","preciseIdentifier":"s:15AWSApiGatewayV216DeleteStageInputV"},{"kind":"text","text":") "},{"kind":"keyword","text":"async"},{"kind":"text","text":" "},{"kind":"keyword","text":"throws"},{"kind":"text","text":" -> "},{"kind":"typeIdentifier","text":"DeleteStageOutputResponse","preciseIdentifier":"s:15AWSApiGatewayV225DeleteStageOutputResponseV"}],"abstract":[{"type":"text","text":"Deletes a Stage."}],"identifier":"doc:\/\/AWSApiGatewayV2\/documentation\/AWSApiGatewayV2\/ApiGatewayV2Client\/deleteStage(input:)","kind":"symbol","type":"topic","url":"\/documentation\/awsapigatewayv2\/apigatewayv2client\/deletestage(input:)"},"doc://AWSApiGatewayV2/documentation/AWSApiGatewayV2/ApiGatewayV2Client/getApi(input:)":{"role":"symbol","title":"getApi(input:)","fragments":[{"kind":"keyword","text":"func"},{"kind":"text","text":" "},{"kind":"identifier","text":"getApi"},{"kind":"text","text":"("},{"kind":"externalParam","text":"input"},{"kind":"text","text":": "},{"kind":"typeIdentifier","text":"GetApiInput","preciseIdentifier":"s:15AWSApiGatewayV211GetApiInputV"},{"kind":"text","text":") "},{"kind":"keyword","text":"async"},{"kind":"text","text":" "},{"kind":"keyword","text":"throws"},{"kind":"text","text":" -> "},{"kind":"typeIdentifier","text":"GetApiOutputResponse","preciseIdentifier":"s:15AWSApiGatewayV220GetApiOutputResponseV"}],"abstract":[{"type":"text","text":"Gets an Api resource."}],"identifier":"doc:\/\/AWSApiGatewayV2\/documentation\/AWSApiGatewayV2\/ApiGatewayV2Client\/getApi(input:)","kind":"symbol","type":"topic","url":"\/documentation\/awsapigatewayv2\/apigatewayv2client\/getapi(input:)"},"doc://AWSApiGatewayV2/documentation/AWSApiGatewayV2/ApiGatewayV2Client/deleteRouteSettings(input:)":{"role":"symbol","title":"deleteRouteSettings(input:)","fragments":[{"kind":"keyword","text":"func"},{"kind":"text","text":" "},{"kind":"identifier","text":"deleteRouteSettings"},{"kind":"text","text":"("},{"kind":"externalParam","text":"input"},{"kind":"text","text":": "},{"kind":"typeIdentifier","text":"DeleteRouteSettingsInput","preciseIdentifier":"s:15AWSApiGatewayV224DeleteRouteSettingsInputV"},{"kind":"text","text":") "},{"kind":"keyword","text":"async"},{"kind":"text","text":" "},{"kind":"keyword","text":"throws"},{"kind":"text","text":" -> "},{"kind":"typeIdentifier","text":"DeleteRouteSettingsOutputResponse","preciseIdentifier":"s:15AWSApiGatewayV233DeleteRouteSettingsOutputResponseV"}],"abstract":[{"type":"text","text":"Deletes the RouteSettings for a stage."}],"identifier":"doc:\/\/AWSApiGatewayV2\/documentation\/AWSApiGatewayV2\/ApiGatewayV2Client\/deleteRouteSettings(input:)","kind":"symbol","type":"topic","url":"\/documentation\/awsapigatewayv2\/apigatewayv2client\/deleteroutesettings(input:)"},"doc://AWSApiGatewayV2/documentation/AWSApiGatewayV2/ApiGatewayV2Client/updateIntegration(input:)":{"role":"symbol","title":"updateIntegration(input:)","fragments":[{"kind":"keyword","text":"func"},{"kind":"text","text":" "},{"kind":"identifier","text":"updateIntegration"},{"kind":"text","text":"("},{"kind":"externalParam","text":"input"},{"kind":"text","text":": "},{"kind":"typeIdentifier","text":"UpdateIntegrationInput","preciseIdentifier":"s:15AWSApiGatewayV222UpdateIntegrationInputV"},{"kind":"text","text":") "},{"kind":"keyword","text":"async"},{"kind":"text","text":" "},{"kind":"keyword","text":"throws"},{"kind":"text","text":" -> "},{"kind":"typeIdentifier","text":"UpdateIntegrationOutputResponse","preciseIdentifier":"s:15AWSApiGatewayV231UpdateIntegrationOutputResponseV"}],"abstract":[{"type":"text","text":"Updates an Integration."}],"identifier":"doc:\/\/AWSApiGatewayV2\/documentation\/AWSApiGatewayV2\/ApiGatewayV2Client\/updateIntegration(input:)","kind":"symbol","type":"topic","url":"\/documentation\/awsapigatewayv2\/apigatewayv2client\/updateintegration(input:)"},"doc://AWSApiGatewayV2/documentation/AWSApiGatewayV2/ApiGatewayV2Client/deleteApi(input:)":{"role":"symbol","title":"deleteApi(input:)","fragments":[{"kind":"keyword","text":"func"},{"kind":"text","text":" "},{"kind":"identifier","text":"deleteApi"},{"kind":"text","text":"("},{"kind":"externalParam","text":"input"},{"kind":"text","text":": "},{"kind":"typeIdentifier","text":"DeleteApiInput","preciseIdentifier":"s:15AWSApiGatewayV214DeleteApiInputV"},{"kind":"text","text":") "},{"kind":"keyword","text":"async"},{"kind":"text","text":" "},{"kind":"keyword","text":"throws"},{"kind":"text","text":" -> "},{"kind":"typeIdentifier","text":"DeleteApiOutputResponse","preciseIdentifier":"s:15AWSApiGatewayV223DeleteApiOutputResponseV"}],"abstract":[{"type":"text","text":"Deletes an Api resource."}],"identifier":"doc:\/\/AWSApiGatewayV2\/documentation\/AWSApiGatewayV2\/ApiGatewayV2Client\/deleteApi(input:)","kind":"symbol","type":"topic","url":"\/documentation\/awsapigatewayv2\/apigatewayv2client\/deleteapi(input:)"},"doc://AWSApiGatewayV2/documentation/AWSApiGatewayV2/ApiGatewayV2Client/resetAuthorizersCache(input:)":{"role":"symbol","title":"resetAuthorizersCache(input:)","fragments":[{"kind":"keyword","text":"func"},{"kind":"text","text":" "},{"kind":"identifier","text":"resetAuthorizersCache"},{"kind":"text","text":"("},{"kind":"externalParam","text":"input"},{"kind":"text","text":": "},{"kind":"typeIdentifier","text":"ResetAuthorizersCacheInput","preciseIdentifier":"s:15AWSApiGatewayV226ResetAuthorizersCacheInputV"},{"kind":"text","text":") "},{"kind":"keyword","text":"async"},{"kind":"text","text":" "},{"kind":"keyword","text":"throws"},{"kind":"text","text":" -> "},{"kind":"typeIdentifier","text":"ResetAuthorizersCacheOutputResponse","preciseIdentifier":"s:15AWSApiGatewayV235ResetAuthorizersCacheOutputResponseV"}],"abstract":[{"type":"text","text":"Resets all authorizer cache entries on a stage. Supported only for HTTP APIs."}],"identifier":"doc:\/\/AWSApiGatewayV2\/documentation\/AWSApiGatewayV2\/ApiGatewayV2Client\/resetAuthorizersCache(input:)","kind":"symbol","type":"topic","url":"\/documentation\/awsapigatewayv2\/apigatewayv2client\/resetauthorizerscache(input:)"},"doc://AWSApiGatewayV2/documentation/AWSApiGatewayV2/ApiGatewayV2Client/getApis(input:)":{"role":"symbol","title":"getApis(input:)","fragments":[{"kind":"keyword","text":"func"},{"kind":"text","text":" "},{"kind":"identifier","text":"getApis"},{"kind":"text","text":"("},{"kind":"externalParam","text":"input"},{"kind":"text","text":": "},{"kind":"typeIdentifier","text":"GetApisInput","preciseIdentifier":"s:15AWSApiGatewayV212GetApisInputV"},{"kind":"text","text":") "},{"kind":"keyword","text":"async"},{"kind":"text","text":" "},{"kind":"keyword","text":"throws"},{"kind":"text","text":" -> "},{"kind":"typeIdentifier","text":"GetApisOutputResponse","preciseIdentifier":"s:15AWSApiGatewayV221GetApisOutputResponseV"}],"abstract":[{"type":"text","text":"Gets a collection of Api resources."}],"identifier":"doc:\/\/AWSApiGatewayV2\/documentation\/AWSApiGatewayV2\/ApiGatewayV2Client\/getApis(input:)","kind":"symbol","type":"topic","url":"\/documentation\/awsapigatewayv2\/apigatewayv2client\/getapis(input:)"},"doc://AWSApiGatewayV2/documentation/AWSApiGatewayV2/ApiGatewayV2Client/createModel(input:)":{"role":"symbol","title":"createModel(input:)","fragments":[{"kind":"keyword","text":"func"},{"kind":"text","text":" "},{"kind":"identifier","text":"createModel"},{"kind":"text","text":"("},{"kind":"externalParam","text":"input"},{"kind":"text","text":": "},{"kind":"typeIdentifier","text":"CreateModelInput","preciseIdentifier":"s:15AWSApiGatewayV216CreateModelInputV"},{"kind":"text","text":") "},{"kind":"keyword","text":"async"},{"kind":"text","text":" "},{"kind":"keyword","text":"throws"},{"kind":"text","text":" -> "},{"kind":"typeIdentifier","text":"CreateModelOutputResponse","preciseIdentifier":"s:15AWSApiGatewayV225CreateModelOutputResponseV"}],"abstract":[{"type":"text","text":"Creates a Model for an API."}],"identifier":"doc:\/\/AWSApiGatewayV2\/documentation\/AWSApiGatewayV2\/ApiGatewayV2Client\/createModel(input:)","kind":"symbol","type":"topic","url":"\/documentation\/awsapigatewayv2\/apigatewayv2client\/createmodel(input:)"},"doc://AWSApiGatewayV2/documentation/AWSApiGatewayV2/ApiGatewayV2Client/createDeployment(input:)":{"role":"symbol","title":"createDeployment(input:)","fragments":[{"kind":"keyword","text":"func"},{"kind":"text","text":" "},{"kind":"identifier","text":"createDeployment"},{"kind":"text","text":"("},{"kind":"externalParam","text":"input"},{"kind":"text","text":": "},{"kind":"typeIdentifier","text":"CreateDeploymentInput","preciseIdentifier":"s:15AWSApiGatewayV221CreateDeploymentInputV"},{"kind":"text","text":") "},{"kind":"keyword","text":"async"},{"kind":"text","text":" "},{"kind":"keyword","text":"throws"},{"kind":"text","text":" -> "},{"kind":"typeIdentifier","text":"CreateDeploymentOutputResponse","preciseIdentifier":"s:15AWSApiGatewayV230CreateDeploymentOutputResponseV"}],"abstract":[{"type":"text","text":"Creates a Deployment for an API."}],"identifier":"doc:\/\/AWSApiGatewayV2\/documentation\/AWSApiGatewayV2\/ApiGatewayV2Client\/createDeployment(input:)","kind":"symbol","type":"topic","url":"\/documentation\/awsapigatewayv2\/apigatewayv2client\/createdeployment(input:)"},"doc://AWSApiGatewayV2/documentation/AWSApiGatewayV2/ApiGatewayV2Client/createStage(input:)":{"role":"symbol","title":"createStage(input:)","fragments":[{"kind":"keyword","text":"func"},{"kind":"text","text":" "},{"kind":"identifier","text":"createStage"},{"kind":"text","text":"("},{"kind":"externalParam","text":"input"},{"kind":"text","text":": "},{"kind":"typeIdentifier","text":"CreateStageInput","preciseIdentifier":"s:15AWSApiGatewayV216CreateStageInputV"},{"kind":"text","text":") "},{"kind":"keyword","text":"async"},{"kind":"text","text":" "},{"kind":"keyword","text":"throws"},{"kind":"text","text":" -> "},{"kind":"typeIdentifier","text":"CreateStageOutputResponse","preciseIdentifier":"s:15AWSApiGatewayV225CreateStageOutputResponseV"}],"abstract":[{"type":"text","text":"Creates a Stage for an API."}],"identifier":"doc:\/\/AWSApiGatewayV2\/documentation\/AWSApiGatewayV2\/ApiGatewayV2Client\/createStage(input:)","kind":"symbol","type":"topic","url":"\/documentation\/awsapigatewayv2\/apigatewayv2client\/createstage(input:)"},"doc://AWSApiGatewayV2/documentation/AWSApiGatewayV2/ApiGatewayV2Client/getIntegrations(input:)":{"role":"symbol","title":"getIntegrations(input:)","fragments":[{"kind":"keyword","text":"func"},{"kind":"text","text":" "},{"kind":"identifier","text":"getIntegrations"},{"kind":"text","text":"("},{"kind":"externalParam","text":"input"},{"kind":"text","text":": "},{"kind":"typeIdentifier","text":"GetIntegrationsInput","preciseIdentifier":"s:15AWSApiGatewayV220GetIntegrationsInputV"},{"kind":"text","text":") "},{"kind":"keyword","text":"async"},{"kind":"text","text":" "},{"kind":"keyword","text":"throws"},{"kind":"text","text":" -> "},{"kind":"typeIdentifier","text":"GetIntegrationsOutputResponse","preciseIdentifier":"s:15AWSApiGatewayV229GetIntegrationsOutputResponseV"}],"abstract":[{"type":"text","text":"Gets the Integrations for an API."}],"identifier":"doc:\/\/AWSApiGatewayV2\/documentation\/AWSApiGatewayV2\/ApiGatewayV2Client\/getIntegrations(input:)","kind":"symbol","type":"topic","url":"\/documentation\/awsapigatewayv2\/apigatewayv2client\/getintegrations(input:)"},"doc://AWSApiGatewayV2/documentation/AWSApiGatewayV2/ApiGatewayV2Client/deleteApiMapping(input:)":{"role":"symbol","title":"deleteApiMapping(input:)","fragments":[{"kind":"keyword","text":"func"},{"kind":"text","text":" "},{"kind":"identifier","text":"deleteApiMapping"},{"kind":"text","text":"("},{"kind":"externalParam","text":"input"},{"kind":"text","text":": "},{"kind":"typeIdentifier","text":"DeleteApiMappingInput","preciseIdentifier":"s:15AWSApiGatewayV221DeleteApiMappingInputV"},{"kind":"text","text":") "},{"kind":"keyword","text":"async"},{"kind":"text","text":" "},{"kind":"keyword","text":"throws"},{"kind":"text","text":" -> "},{"kind":"typeIdentifier","text":"DeleteApiMappingOutputResponse","preciseIdentifier":"s:15AWSApiGatewayV230DeleteApiMappingOutputResponseV"}],"abstract":[{"type":"text","text":"Deletes an API mapping."}],"identifier":"doc:\/\/AWSApiGatewayV2\/documentation\/AWSApiGatewayV2\/ApiGatewayV2Client\/deleteApiMapping(input:)","kind":"symbol","type":"topic","url":"\/documentation\/awsapigatewayv2\/apigatewayv2client\/deleteapimapping(input:)"},"doc://AWSApiGatewayV2/documentation/AWSApiGatewayV2/ApiGatewayV2Client/getRoute(input:)":{"role":"symbol","title":"getRoute(input:)","fragments":[{"kind":"keyword","text":"func"},{"kind":"text","text":" "},{"kind":"identifier","text":"getRoute"},{"kind":"text","text":"("},{"kind":"externalParam","text":"input"},{"kind":"text","text":": "},{"kind":"typeIdentifier","text":"GetRouteInput","preciseIdentifier":"s:15AWSApiGatewayV213GetRouteInputV"},{"kind":"text","text":") "},{"kind":"keyword","text":"async"},{"kind":"text","text":" "},{"kind":"keyword","text":"throws"},{"kind":"text","text":" -> "},{"kind":"typeIdentifier","text":"GetRouteOutputResponse","preciseIdentifier":"s:15AWSApiGatewayV222GetRouteOutputResponseV"}],"abstract":[{"type":"text","text":"Gets a Route."}],"identifier":"doc:\/\/AWSApiGatewayV2\/documentation\/AWSApiGatewayV2\/ApiGatewayV2Client\/getRoute(input:)","kind":"symbol","type":"topic","url":"\/documentation\/awsapigatewayv2\/apigatewayv2client\/getroute(input:)"},"doc://AWSApiGatewayV2/documentation/AWSApiGatewayV2/ApiGatewayV2Client/updateApiMapping(input:)":{"role":"symbol","title":"updateApiMapping(input:)","fragments":[{"kind":"keyword","text":"func"},{"kind":"text","text":" "},{"kind":"identifier","text":"updateApiMapping"},{"kind":"text","text":"("},{"kind":"externalParam","text":"input"},{"kind":"text","text":": "},{"kind":"typeIdentifier","text":"UpdateApiMappingInput","preciseIdentifier":"s:15AWSApiGatewayV221UpdateApiMappingInputV"},{"kind":"text","text":") "},{"kind":"keyword","text":"async"},{"kind":"text","text":" "},{"kind":"keyword","text":"throws"},{"kind":"text","text":" -> "},{"kind":"typeIdentifier","text":"UpdateApiMappingOutputResponse","preciseIdentifier":"s:15AWSApiGatewayV230UpdateApiMappingOutputResponseV"}],"abstract":[{"type":"text","text":"The API mapping."}],"identifier":"doc:\/\/AWSApiGatewayV2\/documentation\/AWSApiGatewayV2\/ApiGatewayV2Client\/updateApiMapping(input:)","kind":"symbol","type":"topic","url":"\/documentation\/awsapigatewayv2\/apigatewayv2client\/updateapimapping(input:)"},"doc://AWSApiGatewayV2/documentation/AWSApiGatewayV2/ApiGatewayV2Client/deleteRouteRequestParameter(input:)":{"role":"symbol","title":"deleteRouteRequestParameter(input:)","fragments":[{"kind":"keyword","text":"func"},{"kind":"text","text":" "},{"kind":"identifier","text":"deleteRouteRequestParameter"},{"kind":"text","text":"("},{"kind":"externalParam","text":"input"},{"kind":"text","text":": "},{"kind":"typeIdentifier","text":"DeleteRouteRequestParameterInput","preciseIdentifier":"s:15AWSApiGatewayV232DeleteRouteRequestParameterInputV"},{"kind":"text","text":") "},{"kind":"keyword","text":"async"},{"kind":"text","text":" "},{"kind":"keyword","text":"throws"},{"kind":"text","text":" -> "},{"kind":"typeIdentifier","text":"DeleteRouteRequestParameterOutputResponse","preciseIdentifier":"s:15AWSApiGatewayV241DeleteRouteRequestParameterOutputResponseV"}],"abstract":[{"type":"text","text":"Deletes a route request parameter."}],"identifier":"doc:\/\/AWSApiGatewayV2\/documentation\/AWSApiGatewayV2\/ApiGatewayV2Client\/deleteRouteRequestParameter(input:)","kind":"symbol","type":"topic","url":"\/documentation\/awsapigatewayv2\/apigatewayv2client\/deleterouterequestparameter(input:)"},"doc://AWSApiGatewayV2/documentation/AWSApiGatewayV2/ApiGatewayV2Client/importApi(input:)":{"role":"symbol","title":"importApi(input:)","fragments":[{"kind":"keyword","text":"func"},{"kind":"text","text":" "},{"kind":"identifier","text":"importApi"},{"kind":"text","text":"("},{"kind":"externalParam","text":"input"},{"kind":"text","text":": "},{"kind":"typeIdentifier","text":"ImportApiInput","preciseIdentifier":"s:15AWSApiGatewayV214ImportApiInputV"},{"kind":"text","text":") "},{"kind":"keyword","text":"async"},{"kind":"text","text":" "},{"kind":"keyword","text":"throws"},{"kind":"text","text":" -> "},{"kind":"typeIdentifier","text":"ImportApiOutputResponse","preciseIdentifier":"s:15AWSApiGatewayV223ImportApiOutputResponseV"}],"abstract":[{"type":"text","text":"Imports an API."}],"identifier":"doc:\/\/AWSApiGatewayV2\/documentation\/AWSApiGatewayV2\/ApiGatewayV2Client\/importApi(input:)","kind":"symbol","type":"topic","url":"\/documentation\/awsapigatewayv2\/apigatewayv2client\/importapi(input:)"},"doc://AWSApiGatewayV2/documentation/AWSApiGatewayV2/ApiGatewayV2Client/updateDomainName(input:)":{"role":"symbol","title":"updateDomainName(input:)","fragments":[{"kind":"keyword","text":"func"},{"kind":"text","text":" "},{"kind":"identifier","text":"updateDomainName"},{"kind":"text","text":"("},{"kind":"externalParam","text":"input"},{"kind":"text","text":": "},{"kind":"typeIdentifier","text":"UpdateDomainNameInput","preciseIdentifier":"s:15AWSApiGatewayV221UpdateDomainNameInputV"},{"kind":"text","text":") "},{"kind":"keyword","text":"async"},{"kind":"text","text":" "},{"kind":"keyword","text":"throws"},{"kind":"text","text":" -> "},{"kind":"typeIdentifier","text":"UpdateDomainNameOutputResponse","preciseIdentifier":"s:15AWSApiGatewayV230UpdateDomainNameOutputResponseV"}],"abstract":[{"type":"text","text":"Updates a domain name."}],"identifier":"doc:\/\/AWSApiGatewayV2\/documentation\/AWSApiGatewayV2\/ApiGatewayV2Client\/updateDomainName(input:)","kind":"symbol","type":"topic","url":"\/documentation\/awsapigatewayv2\/apigatewayv2client\/updatedomainname(input:)"},"doc://AWSApiGatewayV2/documentation/AWSApiGatewayV2/ApiGatewayV2Client/deleteRouteResponse(input:)":{"role":"symbol","title":"deleteRouteResponse(input:)","fragments":[{"kind":"keyword","text":"func"},{"kind":"text","text":" "},{"kind":"identifier","text":"deleteRouteResponse"},{"kind":"text","text":"("},{"kind":"externalParam","text":"input"},{"kind":"text","text":": "},{"kind":"typeIdentifier","text":"DeleteRouteResponseInput","preciseIdentifier":"s:15AWSApiGatewayV224DeleteRouteResponseInputV"},{"kind":"text","text":") "},{"kind":"keyword","text":"async"},{"kind":"text","text":" "},{"kind":"keyword","text":"throws"},{"kind":"text","text":" -> "},{"kind":"typeIdentifier","text":"DeleteRouteResponseOutputResponse","preciseIdentifier":"s:15AWSApiGatewayV2025DeleteRouteResponseOutputF0V"}],"abstract":[{"type":"text","text":"Deletes a RouteResponse."}],"identifier":"doc:\/\/AWSApiGatewayV2\/documentation\/AWSApiGatewayV2\/ApiGatewayV2Client\/deleteRouteResponse(input:)","kind":"symbol","type":"topic","url":"\/documentation\/awsapigatewayv2\/apigatewayv2client\/deleterouteresponse(input:)"},"doc://AWSApiGatewayV2/documentation/AWSApiGatewayV2/ApiGatewayV2Client/getVpcLink(input:)":{"role":"symbol","title":"getVpcLink(input:)","fragments":[{"kind":"keyword","text":"func"},{"kind":"text","text":" "},{"kind":"identifier","text":"getVpcLink"},{"kind":"text","text":"("},{"kind":"externalParam","text":"input"},{"kind":"text","text":": "},{"kind":"typeIdentifier","text":"GetVpcLinkInput","preciseIdentifier":"s:15AWSApiGatewayV215GetVpcLinkInputV"},{"kind":"text","text":") "},{"kind":"keyword","text":"async"},{"kind":"text","text":" "},{"kind":"keyword","text":"throws"},{"kind":"text","text":" -> "},{"kind":"typeIdentifier","text":"GetVpcLinkOutputResponse","preciseIdentifier":"s:15AWSApiGatewayV224GetVpcLinkOutputResponseV"}],"abstract":[{"type":"text","text":"Gets a VPC link."}],"identifier":"doc:\/\/AWSApiGatewayV2\/documentation\/AWSApiGatewayV2\/ApiGatewayV2Client\/getVpcLink(input:)","kind":"symbol","type":"topic","url":"\/documentation\/awsapigatewayv2\/apigatewayv2client\/getvpclink(input:)"},"doc://AWSApiGatewayV2/documentation/AWSApiGatewayV2/ApiGatewayV2Client/getDeployments(input:)":{"role":"symbol","title":"getDeployments(input:)","fragments":[{"kind":"keyword","text":"func"},{"kind":"text","text":" "},{"kind":"identifier","text":"getDeployments"},{"kind":"text","text":"("},{"kind":"externalParam","text":"input"},{"kind":"text","text":": "},{"kind":"typeIdentifier","text":"GetDeploymentsInput","preciseIdentifier":"s:15AWSApiGatewayV219GetDeploymentsInputV"},{"kind":"text","text":") "},{"kind":"keyword","text":"async"},{"kind":"text","text":" "},{"kind":"keyword","text":"throws"},{"kind":"text","text":" -> "},{"kind":"typeIdentifier","text":"GetDeploymentsOutputResponse","preciseIdentifier":"s:15AWSApiGatewayV228GetDeploymentsOutputResponseV"}],"abstract":[{"type":"text","text":"Gets the Deployments for an API."}],"identifier":"doc:\/\/AWSApiGatewayV2\/documentation\/AWSApiGatewayV2\/ApiGatewayV2Client\/getDeployments(input:)","kind":"symbol","type":"topic","url":"\/documentation\/awsapigatewayv2\/apigatewayv2client\/getdeployments(input:)"},"doc://AWSApiGatewayV2/documentation/AWSApiGatewayV2/ApiGatewayV2Client/updateApi(input:)":{"role":"symbol","title":"updateApi(input:)","fragments":[{"kind":"keyword","text":"func"},{"kind":"text","text":" "},{"kind":"identifier","text":"updateApi"},{"kind":"text","text":"("},{"kind":"externalParam","text":"input"},{"kind":"text","text":": "},{"kind":"typeIdentifier","text":"UpdateApiInput","preciseIdentifier":"s:15AWSApiGatewayV214UpdateApiInputV"},{"kind":"text","text":") "},{"kind":"keyword","text":"async"},{"kind":"text","text":" "},{"kind":"keyword","text":"throws"},{"kind":"text","text":" -> "},{"kind":"typeIdentifier","text":"UpdateApiOutputResponse","preciseIdentifier":"s:15AWSApiGatewayV223UpdateApiOutputResponseV"}],"abstract":[{"type":"text","text":"Updates an Api resource."}],"identifier":"doc:\/\/AWSApiGatewayV2\/documentation\/AWSApiGatewayV2\/ApiGatewayV2Client\/updateApi(input:)","kind":"symbol","type":"topic","url":"\/documentation\/awsapigatewayv2\/apigatewayv2client\/updateapi(input:)"},"doc://AWSApiGatewayV2/documentation/AWSApiGatewayV2/ApiGatewayV2Client/updateDeployment(input:)":{"role":"symbol","title":"updateDeployment(input:)","fragments":[{"kind":"keyword","text":"func"},{"kind":"text","text":" "},{"kind":"identifier","text":"updateDeployment"},{"kind":"text","text":"("},{"kind":"externalParam","text":"input"},{"kind":"text","text":": "},{"kind":"typeIdentifier","text":"UpdateDeploymentInput","preciseIdentifier":"s:15AWSApiGatewayV221UpdateDeploymentInputV"},{"kind":"text","text":") "},{"kind":"keyword","text":"async"},{"kind":"text","text":" "},{"kind":"keyword","text":"throws"},{"kind":"text","text":" -> "},{"kind":"typeIdentifier","text":"UpdateDeploymentOutputResponse","preciseIdentifier":"s:15AWSApiGatewayV230UpdateDeploymentOutputResponseV"}],"abstract":[{"type":"text","text":"Updates a Deployment."}],"identifier":"doc:\/\/AWSApiGatewayV2\/documentation\/AWSApiGatewayV2\/ApiGatewayV2Client\/updateDeployment(input:)","kind":"symbol","type":"topic","url":"\/documentation\/awsapigatewayv2\/apigatewayv2client\/updatedeployment(input:)"},"doc://AWSApiGatewayV2/documentation/AWSApiGatewayV2/ApiGatewayV2Client/getStage(input:)":{"role":"symbol","title":"getStage(input:)","fragments":[{"kind":"keyword","text":"func"},{"kind":"text","text":" "},{"kind":"identifier","text":"getStage"},{"kind":"text","text":"("},{"kind":"externalParam","text":"input"},{"kind":"text","text":": "},{"kind":"typeIdentifier","text":"GetStageInput","preciseIdentifier":"s:15AWSApiGatewayV213GetStageInputV"},{"kind":"text","text":") "},{"kind":"keyword","text":"async"},{"kind":"text","text":" "},{"kind":"keyword","text":"throws"},{"kind":"text","text":" -> "},{"kind":"typeIdentifier","text":"GetStageOutputResponse","preciseIdentifier":"s:15AWSApiGatewayV222GetStageOutputResponseV"}],"abstract":[{"type":"text","text":"Gets a Stage."}],"identifier":"doc:\/\/AWSApiGatewayV2\/documentation\/AWSApiGatewayV2\/ApiGatewayV2Client\/getStage(input:)","kind":"symbol","type":"topic","url":"\/documentation\/awsapigatewayv2\/apigatewayv2client\/getstage(input:)"},"doc://AWSApiGatewayV2/documentation/AWSApiGatewayV2/ApiGatewayV2Client/getIntegrationResponse(input:)":{"role":"symbol","title":"getIntegrationResponse(input:)","fragments":[{"kind":"keyword","text":"func"},{"kind":"text","text":" "},{"kind":"identifier","text":"getIntegrationResponse"},{"kind":"text","text":"("},{"kind":"externalParam","text":"input"},{"kind":"text","text":": "},{"kind":"typeIdentifier","text":"GetIntegrationResponseInput","preciseIdentifier":"s:15AWSApiGatewayV227GetIntegrationResponseInputV"},{"kind":"text","text":") "},{"kind":"keyword","text":"async"},{"kind":"text","text":" "},{"kind":"keyword","text":"throws"},{"kind":"text","text":" -> "},{"kind":"typeIdentifier","text":"GetIntegrationResponseOutputResponse","preciseIdentifier":"s:15AWSApiGatewayV2028GetIntegrationResponseOutputF0V"}],"abstract":[{"type":"text","text":"Gets an IntegrationResponses."}],"identifier":"doc:\/\/AWSApiGatewayV2\/documentation\/AWSApiGatewayV2\/ApiGatewayV2Client\/getIntegrationResponse(input:)","kind":"symbol","type":"topic","url":"\/documentation\/awsapigatewayv2\/apigatewayv2client\/getintegrationresponse(input:)"},"doc://AWSApiGatewayV2/documentation/AWSApiGatewayV2/ApiGatewayV2Client/updateModel(input:)":{"role":"symbol","title":"updateModel(input:)","fragments":[{"kind":"keyword","text":"func"},{"kind":"text","text":" "},{"kind":"identifier","text":"updateModel"},{"kind":"text","text":"("},{"kind":"externalParam","text":"input"},{"kind":"text","text":": "},{"kind":"typeIdentifier","text":"UpdateModelInput","preciseIdentifier":"s:15AWSApiGatewayV216UpdateModelInputV"},{"kind":"text","text":") "},{"kind":"keyword","text":"async"},{"kind":"text","text":" "},{"kind":"keyword","text":"throws"},{"kind":"text","text":" -> "},{"kind":"typeIdentifier","text":"UpdateModelOutputResponse","preciseIdentifier":"s:15AWSApiGatewayV225UpdateModelOutputResponseV"}],"abstract":[{"type":"text","text":"Updates a Model."}],"identifier":"doc:\/\/AWSApiGatewayV2\/documentation\/AWSApiGatewayV2\/ApiGatewayV2Client\/updateModel(input:)","kind":"symbol","type":"topic","url":"\/documentation\/awsapigatewayv2\/apigatewayv2client\/updatemodel(input:)"},"doc://AWSApiGatewayV2/documentation/AWSApiGatewayV2/ApiGatewayV2Client/getApiMapping(input:)":{"role":"symbol","title":"getApiMapping(input:)","fragments":[{"kind":"keyword","text":"func"},{"kind":"text","text":" "},{"kind":"identifier","text":"getApiMapping"},{"kind":"text","text":"("},{"kind":"externalParam","text":"input"},{"kind":"text","text":": "},{"kind":"typeIdentifier","text":"GetApiMappingInput","preciseIdentifier":"s:15AWSApiGatewayV218GetApiMappingInputV"},{"kind":"text","text":") "},{"kind":"keyword","text":"async"},{"kind":"text","text":" "},{"kind":"keyword","text":"throws"},{"kind":"text","text":" -> "},{"kind":"typeIdentifier","text":"GetApiMappingOutputResponse","preciseIdentifier":"s:15AWSApiGatewayV227GetApiMappingOutputResponseV"}],"abstract":[{"type":"text","text":"Gets an API mapping."}],"identifier":"doc:\/\/AWSApiGatewayV2\/documentation\/AWSApiGatewayV2\/ApiGatewayV2Client\/getApiMapping(input:)","kind":"symbol","type":"topic","url":"\/documentation\/awsapigatewayv2\/apigatewayv2client\/getapimapping(input:)"},"doc://AWSApiGatewayV2/documentation/AWSApiGatewayV2/ApiGatewayV2Client/getAuthorizer(input:)":{"role":"symbol","title":"getAuthorizer(input:)","fragments":[{"kind":"keyword","text":"func"},{"kind":"text","text":" "},{"kind":"identifier","text":"getAuthorizer"},{"kind":"text","text":"("},{"kind":"externalParam","text":"input"},{"kind":"text","text":": "},{"kind":"typeIdentifier","text":"GetAuthorizerInput","preciseIdentifier":"s:15AWSApiGatewayV218GetAuthorizerInputV"},{"kind":"text","text":") "},{"kind":"keyword","text":"async"},{"kind":"text","text":" "},{"kind":"keyword","text":"throws"},{"kind":"text","text":" -> "},{"kind":"typeIdentifier","text":"GetAuthorizerOutputResponse","preciseIdentifier":"s:15AWSApiGatewayV227GetAuthorizerOutputResponseV"}],"abstract":[{"type":"text","text":"Gets an Authorizer."}],"identifier":"doc:\/\/AWSApiGatewayV2\/documentation\/AWSApiGatewayV2\/ApiGatewayV2Client\/getAuthorizer(input:)","kind":"symbol","type":"topic","url":"\/documentation\/awsapigatewayv2\/apigatewayv2client\/getauthorizer(input:)"},"doc://AWSApiGatewayV2/documentation/AWSApiGatewayV2/ApiGatewayV2Client/updateAuthorizer(input:)":{"role":"symbol","title":"updateAuthorizer(input:)","fragments":[{"kind":"keyword","text":"func"},{"kind":"text","text":" "},{"kind":"identifier","text":"updateAuthorizer"},{"kind":"text","text":"("},{"kind":"externalParam","text":"input"},{"kind":"text","text":": "},{"kind":"typeIdentifier","text":"UpdateAuthorizerInput","preciseIdentifier":"s:15AWSApiGatewayV221UpdateAuthorizerInputV"},{"kind":"text","text":") "},{"kind":"keyword","text":"async"},{"kind":"text","text":" "},{"kind":"keyword","text":"throws"},{"kind":"text","text":" -> "},{"kind":"typeIdentifier","text":"UpdateAuthorizerOutputResponse","preciseIdentifier":"s:15AWSApiGatewayV230UpdateAuthorizerOutputResponseV"}],"abstract":[{"type":"text","text":"Updates an Authorizer."}],"identifier":"doc:\/\/AWSApiGatewayV2\/documentation\/AWSApiGatewayV2\/ApiGatewayV2Client\/updateAuthorizer(input:)","kind":"symbol","type":"topic","url":"\/documentation\/awsapigatewayv2\/apigatewayv2client\/updateauthorizer(input:)"},"doc://AWSApiGatewayV2/documentation/AWSApiGatewayV2/ApiGatewayV2Client/createRoute(input:)":{"role":"symbol","title":"createRoute(input:)","fragments":[{"kind":"keyword","text":"func"},{"kind":"text","text":" "},{"kind":"identifier","text":"createRoute"},{"kind":"text","text":"("},{"kind":"externalParam","text":"input"},{"kind":"text","text":": "},{"kind":"typeIdentifier","text":"CreateRouteInput","preciseIdentifier":"s:15AWSApiGatewayV216CreateRouteInputV"},{"kind":"text","text":") "},{"kind":"keyword","text":"async"},{"kind":"text","text":" "},{"kind":"keyword","text":"throws"},{"kind":"text","text":" -> "},{"kind":"typeIdentifier","text":"CreateRouteOutputResponse","preciseIdentifier":"s:15AWSApiGatewayV225CreateRouteOutputResponseV"}],"abstract":[{"type":"text","text":"Creates a Route for an API."}],"identifier":"doc:\/\/AWSApiGatewayV2\/documentation\/AWSApiGatewayV2\/ApiGatewayV2Client\/createRoute(input:)","kind":"symbol","type":"topic","url":"\/documentation\/awsapigatewayv2\/apigatewayv2client\/createroute(input:)"},"doc://AWSApiGatewayV2/documentation/AWSApiGatewayV2/ApiGatewayV2Client/getRouteResponse(input:)":{"role":"symbol","title":"getRouteResponse(input:)","fragments":[{"kind":"keyword","text":"func"},{"kind":"text","text":" "},{"kind":"identifier","text":"getRouteResponse"},{"kind":"text","text":"("},{"kind":"externalParam","text":"input"},{"kind":"text","text":": "},{"kind":"typeIdentifier","text":"GetRouteResponseInput","preciseIdentifier":"s:15AWSApiGatewayV221GetRouteResponseInputV"},{"kind":"text","text":") "},{"kind":"keyword","text":"async"},{"kind":"text","text":" "},{"kind":"keyword","text":"throws"},{"kind":"text","text":" -> "},{"kind":"typeIdentifier","text":"GetRouteResponseOutputResponse","preciseIdentifier":"s:15AWSApiGatewayV2022GetRouteResponseOutputF0V"}],"abstract":[{"type":"text","text":"Gets a RouteResponse."}],"identifier":"doc:\/\/AWSApiGatewayV2\/documentation\/AWSApiGatewayV2\/ApiGatewayV2Client\/getRouteResponse(input:)","kind":"symbol","type":"topic","url":"\/documentation\/awsapigatewayv2\/apigatewayv2client\/getrouteresponse(input:)"},"doc://AWSApiGatewayV2/documentation/AWSApiGatewayV2/ApiGatewayV2Client/deleteDomainName(input:)":{"role":"symbol","title":"deleteDomainName(input:)","fragments":[{"kind":"keyword","text":"func"},{"kind":"text","text":" "},{"kind":"identifier","text":"deleteDomainName"},{"kind":"text","text":"("},{"kind":"externalParam","text":"input"},{"kind":"text","text":": "},{"kind":"typeIdentifier","text":"DeleteDomainNameInput","preciseIdentifier":"s:15AWSApiGatewayV221DeleteDomainNameInputV"},{"kind":"text","text":") "},{"kind":"keyword","text":"async"},{"kind":"text","text":" "},{"kind":"keyword","text":"throws"},{"kind":"text","text":" -> "},{"kind":"typeIdentifier","text":"DeleteDomainNameOutputResponse","preciseIdentifier":"s:15AWSApiGatewayV230DeleteDomainNameOutputResponseV"}],"abstract":[{"type":"text","text":"Deletes a domain name."}],"identifier":"doc:\/\/AWSApiGatewayV2\/documentation\/AWSApiGatewayV2\/ApiGatewayV2Client\/deleteDomainName(input:)","kind":"symbol","type":"topic","url":"\/documentation\/awsapigatewayv2\/apigatewayv2client\/deletedomainname(input:)"},"doc://AWSApiGatewayV2/documentation/AWSApiGatewayV2/ApiGatewayV2Client/updateRoute(input:)":{"role":"symbol","title":"updateRoute(input:)","fragments":[{"kind":"keyword","text":"func"},{"kind":"text","text":" "},{"kind":"identifier","text":"updateRoute"},{"kind":"text","text":"("},{"kind":"externalParam","text":"input"},{"kind":"text","text":": "},{"kind":"typeIdentifier","text":"UpdateRouteInput","preciseIdentifier":"s:15AWSApiGatewayV216UpdateRouteInputV"},{"kind":"text","text":") "},{"kind":"keyword","text":"async"},{"kind":"text","text":" "},{"kind":"keyword","text":"throws"},{"kind":"text","text":" -> "},{"kind":"typeIdentifier","text":"UpdateRouteOutputResponse","preciseIdentifier":"s:15AWSApiGatewayV225UpdateRouteOutputResponseV"}],"abstract":[{"type":"text","text":"Updates a Route."}],"identifier":"doc:\/\/AWSApiGatewayV2\/documentation\/AWSApiGatewayV2\/ApiGatewayV2Client\/updateRoute(input:)","kind":"symbol","type":"topic","url":"\/documentation\/awsapigatewayv2\/apigatewayv2client\/updateroute(input:)"},"doc://AWSApiGatewayV2/documentation/AWSApiGatewayV2/ApiGatewayV2Client/deleteModel(input:)":{"role":"symbol","title":"deleteModel(input:)","fragments":[{"kind":"keyword","text":"func"},{"kind":"text","text":" "},{"kind":"identifier","text":"deleteModel"},{"kind":"text","text":"("},{"kind":"externalParam","text":"input"},{"kind":"text","text":": "},{"kind":"typeIdentifier","text":"DeleteModelInput","preciseIdentifier":"s:15AWSApiGatewayV216DeleteModelInputV"},{"kind":"text","text":") "},{"kind":"keyword","text":"async"},{"kind":"text","text":" "},{"kind":"keyword","text":"throws"},{"kind":"text","text":" -> "},{"kind":"typeIdentifier","text":"DeleteModelOutputResponse","preciseIdentifier":"s:15AWSApiGatewayV225DeleteModelOutputResponseV"}],"abstract":[{"type":"text","text":"Deletes a Model."}],"identifier":"doc:\/\/AWSApiGatewayV2\/documentation\/AWSApiGatewayV2\/ApiGatewayV2Client\/deleteModel(input:)","kind":"symbol","type":"topic","url":"\/documentation\/awsapigatewayv2\/apigatewayv2client\/deletemodel(input:)"},"doc://AWSApiGatewayV2/documentation/AWSApiGatewayV2/ApiGatewayV2Client/getIntegrationResponses(input:)":{"role":"symbol","title":"getIntegrationResponses(input:)","fragments":[{"kind":"keyword","text":"func"},{"kind":"text","text":" "},{"kind":"identifier","text":"getIntegrationResponses"},{"kind":"text","text":"("},{"kind":"externalParam","text":"input"},{"kind":"text","text":": "},{"kind":"typeIdentifier","text":"GetIntegrationResponsesInput","preciseIdentifier":"s:15AWSApiGatewayV228GetIntegrationResponsesInputV"},{"kind":"text","text":") "},{"kind":"keyword","text":"async"},{"kind":"text","text":" "},{"kind":"keyword","text":"throws"},{"kind":"text","text":" -> "},{"kind":"typeIdentifier","text":"GetIntegrationResponsesOutputResponse","preciseIdentifier":"s:15AWSApiGatewayV237GetIntegrationResponsesOutputResponseV"}],"abstract":[{"type":"text","text":"Gets the IntegrationResponses for an Integration."}],"identifier":"doc:\/\/AWSApiGatewayV2\/documentation\/AWSApiGatewayV2\/ApiGatewayV2Client\/getIntegrationResponses(input:)","kind":"symbol","type":"topic","url":"\/documentation\/awsapigatewayv2\/apigatewayv2client\/getintegrationresponses(input:)"},"doc://AWSApiGatewayV2/documentation/AWSApiGatewayV2/ApiGatewayV2Client":{"role":"symbol","title":"ApiGatewayV2Client","fragments":[{"kind":"keyword","text":"class"},{"kind":"text","text":" "},{"kind":"identifier","text":"ApiGatewayV2Client"}],"abstract":[],"identifier":"doc:\/\/AWSApiGatewayV2\/documentation\/AWSApiGatewayV2\/ApiGatewayV2Client","kind":"symbol","type":"topic","navigatorTitle":[{"kind":"identifier","text":"ApiGatewayV2Client"}],"url":"\/documentation\/awsapigatewayv2\/apigatewayv2client"},"doc://AWSApiGatewayV2/documentation/AWSApiGatewayV2/ApiGatewayV2Client/createApi(input:)":{"role":"symbol","title":"createApi(input:)","fragments":[{"kind":"keyword","text":"func"},{"kind":"text","text":" "},{"kind":"identifier","text":"createApi"},{"kind":"text","text":"("},{"kind":"externalParam","text":"input"},{"kind":"text","text":": "},{"kind":"typeIdentifier","text":"CreateApiInput","preciseIdentifier":"s:15AWSApiGatewayV214CreateApiInputV"},{"kind":"text","text":") "},{"kind":"keyword","text":"async"},{"kind":"text","text":" "},{"kind":"keyword","text":"throws"},{"kind":"text","text":" -> "},{"kind":"typeIdentifier","text":"CreateApiOutputResponse","preciseIdentifier":"s:15AWSApiGatewayV223CreateApiOutputResponseV"}],"abstract":[{"type":"text","text":"Creates an Api resource."}],"identifier":"doc:\/\/AWSApiGatewayV2\/documentation\/AWSApiGatewayV2\/ApiGatewayV2Client\/createApi(input:)","kind":"symbol","type":"topic","url":"\/documentation\/awsapigatewayv2\/apigatewayv2client\/createapi(input:)"},"doc://AWSApiGatewayV2/documentation/AWSApiGatewayV2/ApiGatewayV2Client/deleteCorsConfiguration(input:)":{"role":"symbol","title":"deleteCorsConfiguration(input:)","fragments":[{"kind":"keyword","text":"func"},{"kind":"text","text":" "},{"kind":"identifier","text":"deleteCorsConfiguration"},{"kind":"text","text":"("},{"kind":"externalParam","text":"input"},{"kind":"text","text":": "},{"kind":"typeIdentifier","text":"DeleteCorsConfigurationInput","preciseIdentifier":"s:15AWSApiGatewayV228DeleteCorsConfigurationInputV"},{"kind":"text","text":") "},{"kind":"keyword","text":"async"},{"kind":"text","text":" "},{"kind":"keyword","text":"throws"},{"kind":"text","text":" -> "},{"kind":"typeIdentifier","text":"DeleteCorsConfigurationOutputResponse","preciseIdentifier":"s:15AWSApiGatewayV237DeleteCorsConfigurationOutputResponseV"}],"abstract":[{"type":"text","text":"Deletes a CORS configuration."}],"identifier":"doc:\/\/AWSApiGatewayV2\/documentation\/AWSApiGatewayV2\/ApiGatewayV2Client\/deleteCorsConfiguration(input:)","kind":"symbol","type":"topic","url":"\/documentation\/awsapigatewayv2\/apigatewayv2client\/deletecorsconfiguration(input:)"},"doc://AWSApiGatewayV2/documentation/AWSApiGatewayV2/ApiGatewayV2Client/getVpcLinks(input:)":{"role":"symbol","title":"getVpcLinks(input:)","fragments":[{"kind":"keyword","text":"func"},{"kind":"text","text":" "},{"kind":"identifier","text":"getVpcLinks"},{"kind":"text","text":"("},{"kind":"externalParam","text":"input"},{"kind":"text","text":": "},{"kind":"typeIdentifier","text":"GetVpcLinksInput","preciseIdentifier":"s:15AWSApiGatewayV216GetVpcLinksInputV"},{"kind":"text","text":") "},{"kind":"keyword","text":"async"},{"kind":"text","text":" "},{"kind":"keyword","text":"throws"},{"kind":"text","text":" -> "},{"kind":"typeIdentifier","text":"GetVpcLinksOutputResponse","preciseIdentifier":"s:15AWSApiGatewayV225GetVpcLinksOutputResponseV"}],"abstract":[{"type":"text","text":"Gets a collection of VPC links."}],"identifier":"doc:\/\/AWSApiGatewayV2\/documentation\/AWSApiGatewayV2\/ApiGatewayV2Client\/getVpcLinks(input:)","kind":"symbol","type":"topic","url":"\/documentation\/awsapigatewayv2\/apigatewayv2client\/getvpclinks(input:)"},"doc://AWSApiGatewayV2/documentation/AWSApiGatewayV2/ApiGatewayV2Client/createIntegration(input:)":{"role":"symbol","title":"createIntegration(input:)","fragments":[{"kind":"keyword","text":"func"},{"kind":"text","text":" "},{"kind":"identifier","text":"createIntegration"},{"kind":"text","text":"("},{"kind":"externalParam","text":"input"},{"kind":"text","text":": "},{"kind":"typeIdentifier","text":"CreateIntegrationInput","preciseIdentifier":"s:15AWSApiGatewayV222CreateIntegrationInputV"},{"kind":"text","text":") "},{"kind":"keyword","text":"async"},{"kind":"text","text":" "},{"kind":"keyword","text":"throws"},{"kind":"text","text":" -> "},{"kind":"typeIdentifier","text":"CreateIntegrationOutputResponse","preciseIdentifier":"s:15AWSApiGatewayV231CreateIntegrationOutputResponseV"}],"abstract":[{"type":"text","text":"Creates an Integration."}],"identifier":"doc:\/\/AWSApiGatewayV2\/documentation\/AWSApiGatewayV2\/ApiGatewayV2Client\/createIntegration(input:)","kind":"symbol","type":"topic","url":"\/documentation\/awsapigatewayv2\/apigatewayv2client\/createintegration(input:)"},"doc://AWSApiGatewayV2/documentation/AWSApiGatewayV2/ApiGatewayV2Client/deleteAuthorizer(input:)":{"role":"symbol","title":"deleteAuthorizer(input:)","fragments":[{"kind":"keyword","text":"func"},{"kind":"text","text":" "},{"kind":"identifier","text":"deleteAuthorizer"},{"kind":"text","text":"("},{"kind":"externalParam","text":"input"},{"kind":"text","text":": "},{"kind":"typeIdentifier","text":"DeleteAuthorizerInput","preciseIdentifier":"s:15AWSApiGatewayV221DeleteAuthorizerInputV"},{"kind":"text","text":") "},{"kind":"keyword","text":"async"},{"kind":"text","text":" "},{"kind":"keyword","text":"throws"},{"kind":"text","text":" -> "},{"kind":"typeIdentifier","text":"DeleteAuthorizerOutputResponse","preciseIdentifier":"s:15AWSApiGatewayV230DeleteAuthorizerOutputResponseV"}],"abstract":[{"type":"text","text":"Deletes an Authorizer."}],"identifier":"doc:\/\/AWSApiGatewayV2\/documentation\/AWSApiGatewayV2\/ApiGatewayV2Client\/deleteAuthorizer(input:)","kind":"symbol","type":"topic","url":"\/documentation\/awsapigatewayv2\/apigatewayv2client\/deleteauthorizer(input:)"}}}